[
  {
    "groupId" : "com.typesafe.sbt",
    "artifactId" : "sbt-web",
    "version" : "1.4.4",
    "artifactName" : "sbt-web",
    "projectRef" : {
      "organization" : "sbt",
      "repository" : "sbt-web"
    },
    "description" : "sbt web support",
    "releaseDate" : 1541076422000,
    "resolver" : null,
    "licenses" : [
    ],
    "isNonStandardLib" : false,
    "platform" : "sbt0.13",
    "language" : "2.10",
    "fullScalaVersion" : null,
    "scaladocUrl" : null,
    "versionScheme" : null,
    "developers" : [
    ]
  },
  {
    "groupId" : "com.typesafe.sbt",
    "artifactId" : "sbt-web",
    "version" : "1.4.3",
    "artifactName" : "sbt-web",
    "projectRef" : {
      "organization" : "sbt",
      "repository" : "sbt-web"
    },
    "description" : "sbt web support",
    "releaseDate" : 1504874792000,
    "resolver" : null,
    "licenses" : [
    ],
    "isNonStandardLib" : false,
    "platform" : "sbt0.13",
    "language" : "2.10",
    "fullScalaVersion" : null,
    "scaladocUrl" : null,
    "versionScheme" : null,
    "developers" : [
    ]
  },
  {
    "groupId" : "com.typesafe.sbt",
    "artifactId" : "sbt-web",
    "version" : "1.4.2",
    "artifactName" : "sbt-web",
    "projectRef" : {
      "organization" : "sbt",
      "repository" : "sbt-web"
    },
    "description" : "sbt web support",
    "releaseDate" : 1503496811000,
    "resolver" : null,
    "licenses" : [
    ],
    "isNonStandardLib" : false,
    "platform" : "sbt1.0",
    "language" : "2.12",
    "fullScalaVersion" : null,
    "scaladocUrl" : null,
    "versionScheme" : null,
    "developers" : [
    ]
  },
  {
    "groupId" : "com.typesafe.sbt",
    "artifactId" : "sbt-web",
    "version" : "1.4.1",
    "artifactName" : "sbt-web",
    "projectRef" : {
      "organization" : "sbt",
      "repository" : "sbt-web"
    },
    "description" : "sbt web support",
    "releaseDate" : 1495797293000,
    "resolver" : null,
    "licenses" : [
    ],
    "isNonStandardLib" : false,
    "platform" : "sbt0.13",
    "language" : "2.10",
    "fullScalaVersion" : null,
    "scaladocUrl" : null,
    "versionScheme" : null,
    "developers" : [
    ]
  },
  {
    "groupId" : "com.typesafe.sbt",
    "artifactId" : "sbt-web",
    "version" : "1.4.0",
    "artifactName" : "sbt-web",
    "projectRef" : {
      "organization" : "sbt",
      "repository" : "sbt-web"
    },
    "description" : "sbt web support",
    "releaseDate" : 1460985092000,
    "resolver" : null,
    "licenses" : [
    ],
    "isNonStandardLib" : false,
    "platform" : "sbt0.13",
    "language" : "2.10",
    "fullScalaVersion" : null,
    "scaladocUrl" : null,
    "versionScheme" : null,
    "developers" : [
    ]
  },
  {
    "groupId" : "com.typesafe.sbt",
    "artifactId" : "sbt-web",
    "version" : "1.3.0",
    "artifactName" : "sbt-web",
    "projectRef" : {
      "organization" : "sbt",
      "repository" : "sbt-web"
    },
    "description" : "sbt web support",
    "releaseDate" : 1456229562000,
    "resolver" : null,
    "licenses" : [
    ],
    "isNonStandardLib" : false,
    "platform" : "sbt0.13",
    "language" : "2.10",
    "fullScalaVersion" : null,
    "scaladocUrl" : null,
    "versionScheme" : null,
    "developers" : [
    ]
  },
  {
    "groupId" : "com.typesafe.sbt",
    "artifactId" : "sbt-web",
    "version" : "1.2.3",
    "artifactName" : "sbt-web",
    "projectRef" : {
      "organization" : "sbt",
      "repository" : "sbt-web"
    },
    "description" : "sbt web support",
    "releaseDate" : 1452162814000,
    "resolver" : null,
    "licenses" : [
    ],
    "isNonStandardLib" : false,
    "platform" : "sbt0.13",
    "language" : "2.10",
    "fullScalaVersion" : null,
    "scaladocUrl" : null,
    "versionScheme" : null,
    "developers" : [
    ]
  },
  {
    "groupId" : "com.typesafe.sbt",
    "artifactId" : "sbt-web",
    "version" : "1.2.2",
    "artifactName" : "sbt-web",
    "projectRef" : {
      "organization" : "sbt",
      "repository" : "sbt-web"
    },
    "description" : "sbt web support",
    "releaseDate" : 1435578642000,
    "resolver" : null,
    "licenses" : [
    ],
    "isNonStandardLib" : false,
    "platform" : "sbt0.13",
    "language" : "2.10",
    "fullScalaVersion" : null,
    "scaladocUrl" : null,
    "versionScheme" : null,
    "developers" : [
    ]
  },
  {
    "groupId" : "com.typesafe.sbt",
    "artifactId" : "sbt-web",
    "version" : "1.2.1",
    "artifactName" : "sbt-web",
    "projectRef" : {
      "organization" : "sbt",
      "repository" : "sbt-web"
    },
    "description" : "sbt web support",
    "releaseDate" : 1434961346000,
    "resolver" : null,
    "licenses" : [
    ],
    "isNonStandardLib" : false,
    "platform" : "sbt0.13",
    "language" : "2.10",
    "fullScalaVersion" : null,
    "scaladocUrl" : null,
    "versionScheme" : null,
    "developers" : [
    ]
  },
  {
    "groupId" : "com.typesafe.sbt",
    "artifactId" : "sbt-web",
    "version" : "1.2.0",
    "artifactName" : "sbt-web",
    "projectRef" : {
      "organization" : "sbt",
      "repository" : "sbt-web"
    },
    "description" : "sbt web support",
    "releaseDate" : 1429017397000,
    "resolver" : null,
    "licenses" : [
    ],
    "isNonStandardLib" : false,
    "platform" : "sbt0.13",
    "language" : "2.10",
    "fullScalaVersion" : null,
    "scaladocUrl" : null,
    "versionScheme" : null,
    "developers" : [
    ]
  },
  {
    "groupId" : "com.typesafe.sbt",
    "artifactId" : "sbt-web",
    "version" : "1.1.1",
    "artifactName" : "sbt-web",
    "projectRef" : {
      "organization" : "sbt",
      "repository" : "sbt-web"
    },
    "description" : "sbt-web",
    "releaseDate" : 1411479807000,
    "resolver" : null,
    "licenses" : [
    ],
    "isNonStandardLib" : false,
    "platform" : "sbt0.13",
    "language" : "2.10",
    "fullScalaVersion" : null,
    "scaladocUrl" : null,
    "versionScheme" : null,
    "developers" : [
    ]
  },
  {
    "groupId" : "com.typesafe.sbt",
    "artifactId" : "sbt-web",
    "version" : "1.1.1-20140919-8933ec1",
    "artifactName" : "sbt-web",
    "projectRef" : {
      "organization" : "sbt",
      "repository" : "sbt-web"
    },
    "description" : "sbt-web",
    "releaseDate" : 1411114065000,
    "resolver" : null,
    "licenses" : [
    ],
    "isNonStandardLib" : false,
    "platform" : "sbt0.13",
    "language" : "2.10",
    "fullScalaVersion" : null,
    "scaladocUrl" : null,
    "versionScheme" : null,
    "developers" : [
    ]
  },
  {
    "groupId" : "com.typesafe.sbt",
    "artifactId" : "sbt-web",
    "version" : "1.1.0",
    "artifactName" : "sbt-web",
    "projectRef" : {
      "organization" : "sbt",
      "repository" : "sbt-web"
    },
    "description" : "sbt-web",
    "releaseDate" : 1407161428000,
    "resolver" : null,
    "licenses" : [
    ],
    "isNonStandardLib" : false,
    "platform" : "sbt0.13",
    "language" : "2.10",
    "fullScalaVersion" : null,
    "scaladocUrl" : null,
    "versionScheme" : null,
    "developers" : [
    ]
  },
  {
    "groupId" : "com.typesafe.sbt",
    "artifactId" : "sbt-web",
    "version" : "1.1.0-RC1",
    "artifactName" : "sbt-web",
    "projectRef" : {
      "organization" : "sbt",
      "repository" : "sbt-web"
    },
    "description" : "sbt-web",
    "releaseDate" : 1406634992000,
    "resolver" : null,
    "licenses" : [
    ],
    "isNonStandardLib" : false,
    "platform" : "sbt0.13",
    "language" : "2.10",
    "fullScalaVersion" : null,
    "scaladocUrl" : null,
    "versionScheme" : null,
    "developers" : [
    ]
  },
  {
    "groupId" : "com.typesafe.sbt",
    "artifactId" : "sbt-web",
    "version" : "1.1.0-20140728-caafa4c",
    "artifactName" : "sbt-web",
    "projectRef" : {
      "organization" : "sbt",
      "repository" : "sbt-web"
    },
    "description" : "sbt-web",
    "releaseDate" : 1406627970000,
    "resolver" : null,
    "licenses" : [
    ],
    "isNonStandardLib" : false,
    "platform" : "sbt0.13",
    "language" : "2.10",
    "fullScalaVersion" : null,
    "scaladocUrl" : null,
    "versionScheme" : null,
    "developers" : [
    ]
  },
  {
    "groupId" : "com.typesafe.sbt",
    "artifactId" : "sbt-web",
    "version" : "1.1.0-20140728-37bf46f",
    "artifactName" : "sbt-web",
    "projectRef" : {
      "organization" : "sbt",
      "repository" : "sbt-web"
    },
    "description" : "sbt-web",
    "releaseDate" : 1406566311000,
    "resolver" : null,
    "licenses" : [
    ],
    "isNonStandardLib" : false,
    "platform" : "sbt0.13",
    "language" : "2.10",
    "fullScalaVersion" : null,
    "scaladocUrl" : null,
    "versionScheme" : null,
    "developers" : [
    ]
  },
  {
    "groupId" : "com.typesafe.sbt",
    "artifactId" : "sbt-web",
    "version" : "1.1.0-20140725-c9a26bb",
    "artifactName" : "sbt-web",
    "projectRef" : {
      "organization" : "sbt",
      "repository" : "sbt-web"
    },
    "description" : "sbt-web",
    "releaseDate" : 1406298866000,
    "resolver" : null,
    "licenses" : [
    ],
    "isNonStandardLib" : false,
    "platform" : "sbt0.13",
    "language" : "2.10",
    "fullScalaVersion" : null,
    "scaladocUrl" : null,
    "versionScheme" : null,
    "developers" : [
    ]
  },
  {
    "groupId" : "com.typesafe.sbt",
    "artifactId" : "sbt-web",
    "version" : "1.1.0-20140724-7376faf",
    "artifactName" : "sbt-web",
    "projectRef" : {
      "organization" : "sbt",
      "repository" : "sbt-web"
    },
    "description" : "sbt-web",
    "releaseDate" : 1406216523000,
    "resolver" : null,
    "licenses" : [
    ],
    "isNonStandardLib" : false,
    "platform" : "sbt0.13",
    "language" : "2.10",
    "fullScalaVersion" : null,
    "scaladocUrl" : null,
    "versionScheme" : null,
    "developers" : [
    ]
  },
  {
    "groupId" : "com.typesafe.sbt",
    "artifactId" : "sbt-web",
    "version" : "1.0.3-20140717-c49ba1a",
    "artifactName" : "sbt-web",
    "projectRef" : {
      "organization" : "sbt",
      "repository" : "sbt-web"
    },
    "description" : "sbt-web",
    "releaseDate" : 1405588301000,
    "resolver" : null,
    "licenses" : [
    ],
    "isNonStandardLib" : false,
    "platform" : "sbt0.13",
    "language" : "2.10",
    "fullScalaVersion" : null,
    "scaladocUrl" : null,
    "versionScheme" : null,
    "developers" : [
    ]
  },
  {
    "groupId" : "com.typesafe.sbt",
    "artifactId" : "sbt-web",
    "version" : "1.0.1-2014-06-25-e085c11",
    "artifactName" : "sbt-web",
    "projectRef" : {
      "organization" : "sbt",
      "repository" : "sbt-web"
    },
    "description" : "sbt-web",
    "releaseDate" : 1403691648000,
    "resolver" : null,
    "licenses" : [
    ],
    "isNonStandardLib" : false,
    "platform" : "sbt0.13",
    "language" : "2.10",
    "fullScalaVersion" : null,
    "scaladocUrl" : null,
    "versionScheme" : null,
    "developers" : [
    ]
  },
  {
    "groupId" : "com.typesafe.sbt",
    "artifactId" : "sbt-web",
    "version" : "1.0.2",
    "artifactName" : "sbt-web",
    "projectRef" : {
      "organization" : "sbt",
      "repository" : "sbt-web"
    },
    "description" : "sbt-web",
    "releaseDate" : 1403687503000,
    "resolver" : null,
    "licenses" : [
    ],
    "isNonStandardLib" : false,
    "platform" : "sbt0.13",
    "language" : "2.10",
    "fullScalaVersion" : null,
    "scaladocUrl" : null,
    "versionScheme" : null,
    "developers" : [
    ]
  },
  {
    "groupId" : "com.typesafe.sbt",
    "artifactId" : "sbt-web",
    "version" : "1.0.1",
    "artifactName" : "sbt-web",
    "projectRef" : {
      "organization" : "sbt",
      "repository" : "sbt-web"
    },
    "description" : "sbt-web",
    "releaseDate" : 1403634187000,
    "resolver" : null,
    "licenses" : [
    ],
    "isNonStandardLib" : false,
    "platform" : "sbt0.13",
    "language" : "2.10",
    "fullScalaVersion" : null,
    "scaladocUrl" : null,
    "versionScheme" : null,
    "developers" : [
    ]
  },
  {
    "groupId" : "com.typesafe.sbt",
    "artifactId" : "sbt-web",
    "version" : "1.0.0",
    "artifactName" : "sbt-web",
    "projectRef" : {
      "organization" : "sbt",
      "repository" : "sbt-web"
    },
    "description" : "sbt-web",
    "releaseDate" : 1401279977000,
    "resolver" : null,
    "licenses" : [
    ],
    "isNonStandardLib" : false,
    "platform" : "sbt0.13",
    "language" : "2.10",
    "fullScalaVersion" : null,
    "scaladocUrl" : null,
    "versionScheme" : null,
    "developers" : [
    ]
  },
  {
    "groupId" : "com.typesafe.sbt",
    "artifactId" : "sbt-web",
    "version" : "1.0.0-2014-05-27-5cc167e",
    "artifactName" : "sbt-web",
    "projectRef" : {
      "organization" : "sbt",
      "repository" : "sbt-web"
    },
    "description" : "sbt-web",
    "releaseDate" : 1401205946000,
    "resolver" : null,
    "licenses" : [
    ],
    "isNonStandardLib" : false,
    "platform" : "sbt0.13",
    "language" : "2.10",
    "fullScalaVersion" : null,
    "scaladocUrl" : null,
    "versionScheme" : null,
    "developers" : [
    ]
  },
  {
    "groupId" : "com.typesafe.sbt",
    "artifactId" : "sbt-web",
    "version" : "1.0.0-2014-05-27-a642837",
    "artifactName" : "sbt-web",
    "projectRef" : {
      "organization" : "sbt",
      "repository" : "sbt-web"
    },
    "description" : "sbt-web",
    "releaseDate" : 1401203650000,
    "resolver" : null,
    "licenses" : [
    ],
    "isNonStandardLib" : false,
    "platform" : "sbt0.13",
    "language" : "2.10",
    "fullScalaVersion" : null,
    "scaladocUrl" : null,
    "versionScheme" : null,
    "developers" : [
    ]
  },
  {
    "groupId" : "com.typesafe.sbt",
    "artifactId" : "sbt-web",
    "version" : "1.0.0-2014-05-26-06d5084",
    "artifactName" : "sbt-web",
    "projectRef" : {
      "organization" : "sbt",
      "repository" : "sbt-web"
    },
    "description" : "sbt-web",
    "releaseDate" : 1401106802000,
    "resolver" : null,
    "licenses" : [
    ],
    "isNonStandardLib" : false,
    "platform" : "sbt0.13",
    "language" : "2.10",
    "fullScalaVersion" : null,
    "scaladocUrl" : null,
    "versionScheme" : null,
    "developers" : [
    ]
  },
  {
    "groupId" : "com.typesafe.sbt",
    "artifactId" : "sbt-web",
    "version" : "2014-05-26-06d5084",
    "artifactName" : "sbt-web",
    "projectRef" : {
      "organization" : "sbt",
      "repository" : "sbt-web"
    },
    "description" : "sbt-web",
    "releaseDate" : 1401105202000,
    "resolver" : null,
    "licenses" : [
    ],
    "isNonStandardLib" : false,
    "platform" : "sbt0.13",
    "language" : "2.10",
    "fullScalaVersion" : null,
    "scaladocUrl" : null,
    "versionScheme" : null,
    "developers" : [
    ]
  },
  {
    "groupId" : "com.typesafe.sbt",
    "artifactId" : "sbt-web",
    "version" : "1.0.0-RC3",
    "artifactName" : "sbt-web",
    "projectRef" : {
      "organization" : "sbt",
      "repository" : "sbt-web"
    },
    "description" : "sbt-web",
    "releaseDate" : 1400751243000,
    "resolver" : null,
    "licenses" : [
    ],
    "isNonStandardLib" : false,
    "platform" : "sbt0.13",
    "language" : "2.10",
    "fullScalaVersion" : null,
    "scaladocUrl" : null,
    "versionScheme" : null,
    "developers" : [
    ]
  },
  {
    "groupId" : "com.typesafe.sbt",
    "artifactId" : "sbt-web",
    "version" : "1.0.0-RC2",
    "artifactName" : "sbt-web",
    "projectRef" : {
      "organization" : "sbt",
      "repository" : "sbt-web"
    },
    "description" : "sbt-web",
    "releaseDate" : 1400388081000,
    "resolver" : null,
    "licenses" : [
    ],
    "isNonStandardLib" : false,
    "platform" : "sbt0.13",
    "language" : "2.10",
    "fullScalaVersion" : null,
    "scaladocUrl" : null,
    "versionScheme" : null,
    "developers" : [
    ]
  },
  {
    "groupId" : "com.typesafe.sbt",
    "artifactId" : "sbt-web",
    "version" : "1.0.0-RC1",
    "artifactName" : "sbt-web",
    "projectRef" : {
      "organization" : "sbt",
      "repository" : "sbt-web"
    },
    "description" : "sbt-web",
    "releaseDate" : 1399387527000,
    "resolver" : null,
    "licenses" : [
    ],
    "isNonStandardLib" : false,
    "platform" : "sbt0.13",
    "language" : "2.10",
    "fullScalaVersion" : null,
    "scaladocUrl" : null,
    "versionScheme" : null,
    "developers" : [
    ]
  },
  {
    "groupId" : "com.typesafe.sbt",
    "artifactId" : "sbt-web",
    "version" : "1.0.0-20140506",
    "artifactName" : "sbt-web",
    "projectRef" : {
      "organization" : "sbt",
      "repository" : "sbt-web"
    },
    "description" : "sbt-web",
    "releaseDate" : 1399387186000,
    "resolver" : null,
    "licenses" : [
    ],
    "isNonStandardLib" : false,
    "platform" : "sbt0.13",
    "language" : "2.10",
    "fullScalaVersion" : null,
    "scaladocUrl" : null,
    "versionScheme" : null,
    "developers" : [
    ]
  },
  {
    "groupId" : "com.typesafe.sbt",
    "artifactId" : "sbt-web",
    "version" : "1.0.0-M2",
    "artifactName" : "sbt-web",
    "projectRef" : {
      "organization" : "sbt",
      "repository" : "sbt-web"
    },
    "description" : "sbt-web",
    "releaseDate" : 1396605800000,
    "resolver" : null,
    "licenses" : [
    ],
    "isNonStandardLib" : false,
    "platform" : "sbt0.13",
    "language" : "2.10",
    "fullScalaVersion" : null,
    "scaladocUrl" : null,
    "versionScheme" : null,
    "developers" : [
    ]
  }
]