[
  {
    "groupId" : "org.scala-lang",
    "artifactId" : "scala-dist",
    "version" : "2.12.6",
    "artifactName" : "scala-dist",
    "projectRef" : {
      "organization" : "scala",
      "repository" : "scala"
    },
    "description" : "The Artifacts Distributed with Scala",
    "releaseDate" : 1534412414455,
    "resolver" : {
      "JCenter" : {
        
      }
    },
    "licenses" : [
      "BSD-3-Clause"
    ],
    "isNonStandardLib" : true,
    "platform" : "jvm",
    "language" : "2.12",
    "fullScalaVersion" : null,
    "scaladocUrl" : null,
    "versionScheme" : null,
    "developers" : [
    ]
  },
  {
    "groupId" : "org.scala-lang",
    "artifactId" : "scala-library-all",
    "version" : "2.12.5",
    "artifactName" : "scala-library-all",
    "projectRef" : {
      "organization" : "scala",
      "repository" : "scala"
    },
    "description" : "The Scala Standard Library and Official Modules",
    "releaseDate" : 1530041656757,
    "resolver" : {
      "JCenter" : {
        
      }
    },
    "licenses" : [
      "BSD-3-Clause"
    ],
    "isNonStandardLib" : true,
    "platform" : "jvm",
    "language" : "2.12",
    "fullScalaVersion" : null,
    "scaladocUrl" : null,
    "versionScheme" : null,
    "developers" : [
    ]
  },
  {
    "groupId" : "org.scala-lang",
    "artifactId" : "scala-library-all",
    "version" : "2.12.6",
    "artifactName" : "scala-library-all",
    "projectRef" : {
      "organization" : "scala",
      "repository" : "scala"
    },
    "description" : "The Scala Standard Library and Official Modules",
    "releaseDate" : 1526456630115,
    "resolver" : {
      "JCenter" : {
        
      }
    },
    "licenses" : [
      "BSD-3-Clause"
    ],
    "isNonStandardLib" : true,
    "platform" : "jvm",
    "language" : "2.12",
    "fullScalaVersion" : null,
    "scaladocUrl" : null,
    "versionScheme" : null,
    "developers" : [
    ]
  },
  {
    "groupId" : "org.scala-lang",
    "artifactId" : "scalap",
    "version" : "2.12.6",
    "artifactName" : "scalap",
    "projectRef" : {
      "organization" : "scala",
      "repository" : "scala"
    },
    "description" : "bytecode analysis tool",
    "releaseDate" : 1526302921905,
    "resolver" : {
      "JCenter" : {
        
      }
    },
    "licenses" : [
      "BSD-3-Clause"
    ],
    "isNonStandardLib" : true,
    "platform" : "jvm",
    "language" : "2.12",
    "fullScalaVersion" : null,
    "scaladocUrl" : null,
    "versionScheme" : null,
    "developers" : [
    ]
  },
  {
    "groupId" : "org.scala-lang",
    "artifactId" : "scala-library",
    "version" : "2.12.6",
    "artifactName" : "scala-library",
    "projectRef" : {
      "organization" : "scala",
      "repository" : "scala"
    },
    "description" : "Standard library for the Scala Programming Language",
    "releaseDate" : 1526283263932,
    "resolver" : {
      "JCenter" : {
        
      }
    },
    "licenses" : [
      "BSD-3-Clause"
    ],
    "isNonStandardLib" : true,
    "platform" : "jvm",
    "language" : "2.12",
    "fullScalaVersion" : null,
    "scaladocUrl" : null,
    "versionScheme" : null,
    "developers" : [
    ]
  },
  {
    "groupId" : "org.scala-lang",
    "artifactId" : "scala-reflect",
    "version" : "2.12.6",
    "artifactName" : "scala-reflect",
    "projectRef" : {
      "organization" : "scala",
      "repository" : "scala"
    },
    "description" : "Compiler for the Scala Programming Language",
    "releaseDate" : 1526282395312,
    "resolver" : {
      "JCenter" : {
        
      }
    },
    "licenses" : [
      "BSD-3-Clause"
    ],
    "isNonStandardLib" : true,
    "platform" : "jvm",
    "language" : "2.12",
    "fullScalaVersion" : null,
    "scaladocUrl" : null,
    "versionScheme" : null,
    "developers" : [
    ]
  },
  {
    "groupId" : "org.scala-lang",
    "artifactId" : "scala-compiler",
    "version" : "2.12.6",
    "artifactName" : "scala-compiler",
    "projectRef" : {
      "organization" : "scala",
      "repository" : "scala"
    },
    "description" : "Compiler for the Scala Programming Language",
    "releaseDate" : 1526282380246,
    "resolver" : {
      "JCenter" : {
        
      }
    },
    "licenses" : [
      "BSD-3-Clause"
    ],
    "isNonStandardLib" : true,
    "platform" : "jvm",
    "language" : "2.12",
    "fullScalaVersion" : null,
    "scaladocUrl" : null,
    "versionScheme" : null,
    "developers" : [
    ]
  },
  {
    "groupId" : "org.scala-lang",
    "artifactId" : "scalap",
    "version" : "2.12.5",
    "artifactName" : "scalap",
    "projectRef" : {
      "organization" : "scala",
      "repository" : "scala"
    },
    "description" : "bytecode analysis tool",
    "releaseDate" : 1521696985634,
    "resolver" : {
      "JCenter" : {
        
      }
    },
    "licenses" : [
      "BSD-3-Clause"
    ],
    "isNonStandardLib" : true,
    "platform" : "jvm",
    "language" : "2.12",
    "fullScalaVersion" : null,
    "scaladocUrl" : null,
    "versionScheme" : null,
    "developers" : [
    ]
  },
  {
    "groupId" : "org.scala-lang",
    "artifactId" : "scala-dist",
    "version" : "2.12.5",
    "artifactName" : "scala-dist",
    "projectRef" : {
      "organization" : "scala",
      "repository" : "scala"
    },
    "description" : "The Artifacts Distributed with Scala",
    "releaseDate" : 1521566303843,
    "resolver" : {
      "JCenter" : {
        
      }
    },
    "licenses" : [
      "BSD-3-Clause"
    ],
    "isNonStandardLib" : true,
    "platform" : "jvm",
    "language" : "2.12",
    "fullScalaVersion" : null,
    "scaladocUrl" : null,
    "versionScheme" : null,
    "developers" : [
    ]
  },
  {
    "groupId" : "org.scala-lang",
    "artifactId" : "scala-reflect",
    "version" : "2.12.5",
    "artifactName" : "scala-reflect",
    "projectRef" : {
      "organization" : "scala",
      "repository" : "scala"
    },
    "description" : "Compiler for the Scala Programming Language",
    "releaseDate" : 1521527268279,
    "resolver" : {
      "JCenter" : {
        
      }
    },
    "licenses" : [
      "BSD-3-Clause"
    ],
    "isNonStandardLib" : true,
    "platform" : "jvm",
    "language" : "2.12",
    "fullScalaVersion" : null,
    "scaladocUrl" : null,
    "versionScheme" : null,
    "developers" : [
    ]
  },
  {
    "groupId" : "org.scala-lang",
    "artifactId" : "scala-compiler",
    "version" : "2.12.5",
    "artifactName" : "scala-compiler",
    "projectRef" : {
      "organization" : "scala",
      "repository" : "scala"
    },
    "description" : "Compiler for the Scala Programming Language",
    "releaseDate" : 1521527266911,
    "resolver" : {
      "JCenter" : {
        
      }
    },
    "licenses" : [
      "BSD-3-Clause"
    ],
    "isNonStandardLib" : true,
    "platform" : "jvm",
    "language" : "2.12",
    "fullScalaVersion" : null,
    "scaladocUrl" : null,
    "versionScheme" : null,
    "developers" : [
    ]
  },
  {
    "groupId" : "org.scala-lang",
    "artifactId" : "scala-library",
    "version" : "2.12.5",
    "artifactName" : "scala-library",
    "projectRef" : {
      "organization" : "scala",
      "repository" : "scala"
    },
    "description" : "Standard library for the Scala Programming Language",
    "releaseDate" : 1521527264678,
    "resolver" : {
      "JCenter" : {
        
      }
    },
    "licenses" : [
      "BSD-3-Clause"
    ],
    "isNonStandardLib" : true,
    "platform" : "jvm",
    "language" : "2.12",
    "fullScalaVersion" : null,
    "scaladocUrl" : null,
    "versionScheme" : null,
    "developers" : [
    ]
  },
  {
    "groupId" : "org.scala-lang",
    "artifactId" : "scalap",
    "version" : "2.10.7",
    "artifactName" : "scalap",
    "projectRef" : {
      "organization" : "scala",
      "repository" : "scala"
    },
    "description" : "bytecode analysis tool",
    "releaseDate" : 1511356728758,
    "resolver" : {
      "JCenter" : {
        
      }
    },
    "licenses" : [
      "BSD-3-Clause"
    ],
    "isNonStandardLib" : true,
    "platform" : "jvm",
    "language" : "2.10",
    "fullScalaVersion" : null,
    "scaladocUrl" : null,
    "versionScheme" : null,
    "developers" : [
    ]
  },
  {
    "groupId" : "org.scala-lang",
    "artifactId" : "scala-actors",
    "version" : "2.11.12",
    "artifactName" : "scala-actors",
    "projectRef" : {
      "organization" : "scala",
      "repository" : "scala"
    },
    "description" : "Deprecated Actors Library for Scala",
    "releaseDate" : 1511347976349,
    "resolver" : {
      "JCenter" : {
        
      }
    },
    "licenses" : [
      "BSD-3-Clause"
    ],
    "isNonStandardLib" : true,
    "platform" : "jvm",
    "language" : "2.11",
    "fullScalaVersion" : null,
    "scaladocUrl" : null,
    "versionScheme" : null,
    "developers" : [
    ]
  },
  {
    "groupId" : "org.scala-lang",
    "artifactId" : "scala-dist",
    "version" : "2.12.4",
    "artifactName" : "scala-dist",
    "projectRef" : {
      "organization" : "scala",
      "repository" : "scala"
    },
    "description" : "The Artifacts Distributed with Scala",
    "releaseDate" : 1511294727081,
    "resolver" : {
      "JCenter" : {
        
      }
    },
    "licenses" : [
      "BSD-3-Clause"
    ],
    "isNonStandardLib" : true,
    "platform" : "jvm",
    "language" : "2.12",
    "fullScalaVersion" : null,
    "scaladocUrl" : null,
    "versionScheme" : null,
    "developers" : [
    ]
  },
  {
    "groupId" : "org.scala-lang",
    "artifactId" : "scala-dist",
    "version" : "2.11.12",
    "artifactName" : "scala-dist",
    "projectRef" : {
      "organization" : "scala",
      "repository" : "scala"
    },
    "description" : "The Artifacts Distributed with Scala",
    "releaseDate" : 1511294721888,
    "resolver" : {
      "JCenter" : {
        
      }
    },
    "licenses" : [
      "BSD-3-Clause"
    ],
    "isNonStandardLib" : true,
    "platform" : "jvm",
    "language" : "2.11",
    "fullScalaVersion" : null,
    "scaladocUrl" : null,
    "versionScheme" : null,
    "developers" : [
    ]
  },
  {
    "groupId" : "org.scala-lang",
    "artifactId" : "scala-library-all",
    "version" : "2.11.12",
    "artifactName" : "scala-library-all",
    "projectRef" : {
      "organization" : "scala",
      "repository" : "scala"
    },
    "description" : "The Scala Standard Library and Official Modules",
    "releaseDate" : 1511294679965,
    "resolver" : {
      "JCenter" : {
        
      }
    },
    "licenses" : [
      "BSD-3-Clause"
    ],
    "isNonStandardLib" : true,
    "platform" : "jvm",
    "language" : "2.11",
    "fullScalaVersion" : null,
    "scaladocUrl" : null,
    "versionScheme" : null,
    "developers" : [
    ]
  },
  {
    "groupId" : "org.scala-lang",
    "artifactId" : "scala-actors",
    "version" : "2.10.7",
    "artifactName" : "scala-actors",
    "projectRef" : {
      "organization" : "scala",
      "repository" : "scala"
    },
    "description" : "Deprecated Actors Library for Scala",
    "releaseDate" : 1511294662627,
    "resolver" : {
      "JCenter" : {
        
      }
    },
    "licenses" : [
      "BSD-3-Clause"
    ],
    "isNonStandardLib" : true,
    "platform" : "jvm",
    "language" : "2.10",
    "fullScalaVersion" : null,
    "scaladocUrl" : null,
    "versionScheme" : null,
    "developers" : [
    ]
  },
  {
    "groupId" : "org.scala-lang",
    "artifactId" : "scalap",
    "version" : "2.11.12",
    "artifactName" : "scalap",
    "projectRef" : {
      "organization" : "scala",
      "repository" : "scala"
    },
    "description" : "bytecode analysis tool",
    "releaseDate" : 1510155904747,
    "resolver" : {
      "JCenter" : {
        
      }
    },
    "licenses" : [
      "BSD-3-Clause"
    ],
    "isNonStandardLib" : true,
    "platform" : "jvm",
    "language" : "2.11",
    "fullScalaVersion" : null,
    "scaladocUrl" : null,
    "versionScheme" : null,
    "developers" : [
    ]
  },
  {
    "groupId" : "org.scala-lang",
    "artifactId" : "scala-compiler",
    "version" : "2.10.7",
    "artifactName" : "scala-compiler",
    "projectRef" : {
      "organization" : "scala",
      "repository" : "scala"
    },
    "description" : "Compiler for the Scala Programming Language",
    "releaseDate" : 1510115248166,
    "resolver" : {
      "JCenter" : {
        
      }
    },
    "licenses" : [
      "BSD-3-Clause"
    ],
    "isNonStandardLib" : true,
    "platform" : "jvm",
    "language" : "2.10",
    "fullScalaVersion" : null,
    "scaladocUrl" : null,
    "versionScheme" : null,
    "developers" : [
    ]
  },
  {
    "groupId" : "org.scala-lang",
    "artifactId" : "scala-reflect",
    "version" : "2.10.7",
    "artifactName" : "scala-reflect",
    "projectRef" : {
      "organization" : "scala",
      "repository" : "scala"
    },
    "description" : "Compiler for the Scala Programming Language",
    "releaseDate" : 1510059329233,
    "resolver" : {
      "JCenter" : {
        
      }
    },
    "licenses" : [
      "BSD-3-Clause"
    ],
    "isNonStandardLib" : true,
    "platform" : "jvm",
    "language" : "2.10",
    "fullScalaVersion" : null,
    "scaladocUrl" : null,
    "versionScheme" : null,
    "developers" : [
    ]
  },
  {
    "groupId" : "org.scala-lang",
    "artifactId" : "scala-library",
    "version" : "2.10.7",
    "artifactName" : "scala-library",
    "projectRef" : {
      "organization" : "scala",
      "repository" : "scala"
    },
    "description" : "Standard library for the Scala Programming Language",
    "releaseDate" : 1510022117871,
    "resolver" : {
      "JCenter" : {
        
      }
    },
    "licenses" : [
      "BSD-3-Clause"
    ],
    "isNonStandardLib" : true,
    "platform" : "jvm",
    "language" : "2.10",
    "fullScalaVersion" : null,
    "scaladocUrl" : null,
    "versionScheme" : null,
    "developers" : [
    ]
  },
  {
    "groupId" : "org.scala-lang",
    "artifactId" : "scala-compiler",
    "version" : "2.11.12",
    "artifactName" : "scala-compiler",
    "projectRef" : {
      "organization" : "scala",
      "repository" : "scala"
    },
    "description" : "Compiler for the Scala Programming Language",
    "releaseDate" : 1510002940830,
    "resolver" : {
      "JCenter" : {
        
      }
    },
    "licenses" : [
      "BSD-3-Clause"
    ],
    "isNonStandardLib" : true,
    "platform" : "jvm",
    "language" : "2.11",
    "fullScalaVersion" : null,
    "scaladocUrl" : null,
    "versionScheme" : null,
    "developers" : [
    ]
  },
  {
    "groupId" : "org.scala-lang",
    "artifactId" : "scala-reflect",
    "version" : "2.11.12",
    "artifactName" : "scala-reflect",
    "projectRef" : {
      "organization" : "scala",
      "repository" : "scala"
    },
    "description" : "Compiler for the Scala Programming Language",
    "releaseDate" : 1510002934594,
    "resolver" : {
      "JCenter" : {
        
      }
    },
    "licenses" : [
      "BSD-3-Clause"
    ],
    "isNonStandardLib" : true,
    "platform" : "jvm",
    "language" : "2.11",
    "fullScalaVersion" : null,
    "scaladocUrl" : null,
    "versionScheme" : null,
    "developers" : [
    ]
  },
  {
    "groupId" : "org.scala-lang",
    "artifactId" : "scala-library",
    "version" : "2.11.12",
    "artifactName" : "scala-library",
    "projectRef" : {
      "organization" : "scala",
      "repository" : "scala"
    },
    "description" : "Standard library for the Scala Programming Language",
    "releaseDate" : 1510002456770,
    "resolver" : {
      "JCenter" : {
        
      }
    },
    "licenses" : [
      "BSD-3-Clause"
    ],
    "isNonStandardLib" : true,
    "platform" : "jvm",
    "language" : "2.11",
    "fullScalaVersion" : null,
    "scaladocUrl" : null,
    "versionScheme" : null,
    "developers" : [
    ]
  },
  {
    "groupId" : "org.scala-lang",
    "artifactId" : "scala-library-all",
    "version" : "2.12.4",
    "artifactName" : "scala-library-all",
    "projectRef" : {
      "organization" : "scala",
      "repository" : "scala"
    },
    "description" : "The Scala Standard Library and Official Modules",
    "releaseDate" : 1509568003351,
    "resolver" : {
      "JCenter" : {
        
      }
    },
    "licenses" : [
      "BSD-3-Clause"
    ],
    "isNonStandardLib" : true,
    "platform" : "jvm",
    "language" : "2.12",
    "fullScalaVersion" : null,
    "scaladocUrl" : null,
    "versionScheme" : null,
    "developers" : [
    ]
  },
  {
    "groupId" : "org.scala-lang",
    "artifactId" : "scalap",
    "version" : "2.12.4",
    "artifactName" : "scalap",
    "projectRef" : {
      "organization" : "scala",
      "repository" : "scala"
    },
    "description" : "bytecode analysis tool",
    "releaseDate" : 1508362487719,
    "resolver" : {
      "JCenter" : {
        
      }
    },
    "licenses" : [
      "BSD-3-Clause"
    ],
    "isNonStandardLib" : true,
    "platform" : "jvm",
    "language" : "2.12",
    "fullScalaVersion" : null,
    "scaladocUrl" : null,
    "versionScheme" : null,
    "developers" : [
    ]
  },
  {
    "groupId" : "org.scala-lang",
    "artifactId" : "scala-reflect",
    "version" : "2.12.4",
    "artifactName" : "scala-reflect",
    "projectRef" : {
      "organization" : "scala",
      "repository" : "scala"
    },
    "description" : "Compiler for the Scala Programming Language",
    "releaseDate" : 1508282778852,
    "resolver" : {
      "JCenter" : {
        
      }
    },
    "licenses" : [
      "BSD-3-Clause"
    ],
    "isNonStandardLib" : true,
    "platform" : "jvm",
    "language" : "2.12",
    "fullScalaVersion" : null,
    "scaladocUrl" : null,
    "versionScheme" : null,
    "developers" : [
    ]
  },
  {
    "groupId" : "org.scala-lang",
    "artifactId" : "scala-compiler",
    "version" : "2.12.4",
    "artifactName" : "scala-compiler",
    "projectRef" : {
      "organization" : "scala",
      "repository" : "scala"
    },
    "description" : "Compiler for the Scala Programming Language",
    "releaseDate" : 1508282775071,
    "resolver" : {
      "JCenter" : {
        
      }
    },
    "licenses" : [
      "BSD-3-Clause"
    ],
    "isNonStandardLib" : true,
    "platform" : "jvm",
    "language" : "2.12",
    "fullScalaVersion" : null,
    "scaladocUrl" : null,
    "versionScheme" : null,
    "developers" : [
    ]
  },
  {
    "groupId" : "org.scala-lang",
    "artifactId" : "scala-library",
    "version" : "2.12.4",
    "artifactName" : "scala-library",
    "projectRef" : {
      "organization" : "scala",
      "repository" : "scala"
    },
    "description" : "Standard library for the Scala Programming Language",
    "releaseDate" : 1508282771345,
    "resolver" : {
      "JCenter" : {
        
      }
    },
    "licenses" : [
      "BSD-3-Clause"
    ],
    "isNonStandardLib" : true,
    "platform" : "jvm",
    "language" : "2.12",
    "fullScalaVersion" : null,
    "scaladocUrl" : null,
    "versionScheme" : null,
    "developers" : [
    ]
  },
  {
    "groupId" : "org.scala-lang",
    "artifactId" : "scala-dist",
    "version" : "2.12.3",
    "artifactName" : "scala-dist",
    "projectRef" : {
      "organization" : "scala",
      "repository" : "scala"
    },
    "description" : "The Artifacts Distributed with Scala",
    "releaseDate" : 1505748998575,
    "resolver" : {
      "JCenter" : {
        
      }
    },
    "licenses" : [
      "BSD-3-Clause"
    ],
    "isNonStandardLib" : true,
    "platform" : "jvm",
    "language" : "2.12",
    "fullScalaVersion" : null,
    "scaladocUrl" : null,
    "versionScheme" : null,
    "developers" : [
    ]
  },
  {
    "groupId" : "org.scala-lang",
    "artifactId" : "scala-library-all",
    "version" : "2.12.3",
    "artifactName" : "scala-library-all",
    "projectRef" : {
      "organization" : "scala",
      "repository" : "scala"
    },
    "description" : "The Scala Standard Library and Official Modules",
    "releaseDate" : 1501684317732,
    "resolver" : {
      "JCenter" : {
        
      }
    },
    "licenses" : [
      "BSD-3-Clause"
    ],
    "isNonStandardLib" : true,
    "platform" : "jvm",
    "language" : "2.12",
    "fullScalaVersion" : null,
    "scaladocUrl" : null,
    "versionScheme" : null,
    "developers" : [
    ]
  },
  {
    "groupId" : "org.scala-lang",
    "artifactId" : "scala-compiler",
    "version" : "2.12.3",
    "artifactName" : "scala-compiler",
    "projectRef" : {
      "organization" : "scala",
      "repository" : "scala"
    },
    "description" : "Compiler for the Scala Programming Language",
    "releaseDate" : 1501186222465,
    "resolver" : {
      "JCenter" : {
        
      }
    },
    "licenses" : [
      "BSD-3-Clause"
    ],
    "isNonStandardLib" : true,
    "platform" : "jvm",
    "language" : "2.12",
    "fullScalaVersion" : null,
    "scaladocUrl" : null,
    "versionScheme" : null,
    "developers" : [
    ]
  },
  {
    "groupId" : "org.scala-lang",
    "artifactId" : "scala-library",
    "version" : "2.12.3",
    "artifactName" : "scala-library",
    "projectRef" : {
      "organization" : "scala",
      "repository" : "scala"
    },
    "description" : "Standard library for the Scala Programming Language",
    "releaseDate" : 1501186219364,
    "resolver" : {
      "JCenter" : {
        
      }
    },
    "licenses" : [
      "BSD-3-Clause"
    ],
    "isNonStandardLib" : true,
    "platform" : "jvm",
    "language" : "2.12",
    "fullScalaVersion" : null,
    "scaladocUrl" : null,
    "versionScheme" : null,
    "developers" : [
    ]
  },
  {
    "groupId" : "org.scala-lang",
    "artifactId" : "scala-dist",
    "version" : "2.12.2",
    "artifactName" : "scala-dist",
    "projectRef" : {
      "organization" : "scala",
      "repository" : "scala"
    },
    "description" : "The Artifacts Distributed with Scala",
    "releaseDate" : 1494374968630,
    "resolver" : {
      "JCenter" : {
        
      }
    },
    "licenses" : [
      "BSD-3-Clause"
    ],
    "isNonStandardLib" : true,
    "platform" : "jvm",
    "language" : "2.12",
    "fullScalaVersion" : null,
    "scaladocUrl" : null,
    "versionScheme" : null,
    "developers" : [
    ]
  },
  {
    "groupId" : "org.scala-lang",
    "artifactId" : "scala-dist",
    "version" : "2.11.11",
    "artifactName" : "scala-dist",
    "projectRef" : {
      "organization" : "scala",
      "repository" : "scala"
    },
    "description" : "The Artifacts Distributed with Scala",
    "releaseDate" : 1494374963157,
    "resolver" : {
      "JCenter" : {
        
      }
    },
    "licenses" : [
      "BSD-3-Clause"
    ],
    "isNonStandardLib" : true,
    "platform" : "jvm",
    "language" : "2.11",
    "fullScalaVersion" : null,
    "scaladocUrl" : null,
    "versionScheme" : null,
    "developers" : [
    ]
  },
  {
    "groupId" : "org.scala-lang",
    "artifactId" : "scala-library-all",
    "version" : "2.11.10",
    "artifactName" : "scala-library-all",
    "projectRef" : {
      "organization" : "scala",
      "repository" : "scala"
    },
    "description" : "The Scala Standard Library and Official Modules",
    "releaseDate" : 1494247089360,
    "resolver" : {
      "JCenter" : {
        
      }
    },
    "licenses" : [
      "BSD-3-Clause"
    ],
    "isNonStandardLib" : true,
    "platform" : "jvm",
    "language" : "2.11",
    "fullScalaVersion" : null,
    "scaladocUrl" : null,
    "versionScheme" : null,
    "developers" : [
    ]
  },
  {
    "groupId" : "org.scala-lang",
    "artifactId" : "scala-dist",
    "version" : "2.11.10",
    "artifactName" : "scala-dist",
    "projectRef" : {
      "organization" : "scala",
      "repository" : "scala"
    },
    "description" : "The Artifacts Distributed with Scala",
    "releaseDate" : 1494247086162,
    "resolver" : {
      "JCenter" : {
        
      }
    },
    "licenses" : [
      "BSD-3-Clause"
    ],
    "isNonStandardLib" : true,
    "platform" : "jvm",
    "language" : "2.11",
    "fullScalaVersion" : null,
    "scaladocUrl" : null,
    "versionScheme" : null,
    "developers" : [
    ]
  },
  {
    "groupId" : "org.scala-lang",
    "artifactId" : "scala-actors",
    "version" : "2.11.10",
    "artifactName" : "scala-actors",
    "projectRef" : {
      "organization" : "scala",
      "repository" : "scala"
    },
    "description" : "Deprecated Actors Library for Scala",
    "releaseDate" : 1494247080073,
    "resolver" : {
      "JCenter" : {
        
      }
    },
    "licenses" : [
      "BSD-3-Clause"
    ],
    "isNonStandardLib" : true,
    "platform" : "jvm",
    "language" : "2.11",
    "fullScalaVersion" : null,
    "scaladocUrl" : null,
    "versionScheme" : null,
    "developers" : [
    ]
  },
  {
    "groupId" : "org.scala-lang",
    "artifactId" : "scala-library-all",
    "version" : "2.11.9",
    "artifactName" : "scala-library-all",
    "projectRef" : {
      "organization" : "scala",
      "repository" : "scala"
    },
    "description" : "The Scala Standard Library and Official Modules",
    "releaseDate" : 1493884887348,
    "resolver" : {
      "JCenter" : {
        
      }
    },
    "licenses" : [
      "BSD-3-Clause"
    ],
    "isNonStandardLib" : true,
    "platform" : "jvm",
    "language" : "2.11",
    "fullScalaVersion" : null,
    "scaladocUrl" : null,
    "versionScheme" : null,
    "developers" : [
    ]
  },
  {
    "groupId" : "org.scala-lang",
    "artifactId" : "scala-dist",
    "version" : "2.11.9",
    "artifactName" : "scala-dist",
    "projectRef" : {
      "organization" : "scala",
      "repository" : "scala"
    },
    "description" : "The Artifacts Distributed with Scala",
    "releaseDate" : 1493884884154,
    "resolver" : {
      "JCenter" : {
        
      }
    },
    "licenses" : [
      "BSD-3-Clause"
    ],
    "isNonStandardLib" : true,
    "platform" : "jvm",
    "language" : "2.11",
    "fullScalaVersion" : null,
    "scaladocUrl" : null,
    "versionScheme" : null,
    "developers" : [
    ]
  },
  {
    "groupId" : "org.scala-lang",
    "artifactId" : "scala-library-all",
    "version" : "2.11.11",
    "artifactName" : "scala-library-all",
    "projectRef" : {
      "organization" : "scala",
      "repository" : "scala"
    },
    "description" : "The Scala Standard Library and Official Modules",
    "releaseDate" : 1493032339143,
    "resolver" : {
      "JCenter" : {
        
      }
    },
    "licenses" : [
      "BSD-3-Clause"
    ],
    "isNonStandardLib" : true,
    "platform" : "jvm",
    "language" : "2.11",
    "fullScalaVersion" : null,
    "scaladocUrl" : null,
    "versionScheme" : null,
    "developers" : [
    ]
  },
  {
    "groupId" : "org.scala-lang",
    "artifactId" : "scala-actors",
    "version" : "2.11.11",
    "artifactName" : "scala-actors",
    "projectRef" : {
      "organization" : "scala",
      "repository" : "scala"
    },
    "description" : "Deprecated Actors Library for Scala",
    "releaseDate" : 1492769842680,
    "resolver" : {
      "JCenter" : {
        
      }
    },
    "licenses" : [
      "BSD-3-Clause"
    ],
    "isNonStandardLib" : true,
    "platform" : "jvm",
    "language" : "2.11",
    "fullScalaVersion" : null,
    "scaladocUrl" : null,
    "versionScheme" : null,
    "developers" : [
    ]
  },
  {
    "groupId" : "org.scala-lang",
    "artifactId" : "scala-library-all",
    "version" : "2.12.2",
    "artifactName" : "scala-library-all",
    "projectRef" : {
      "organization" : "scala",
      "repository" : "scala"
    },
    "description" : "The Scala Standard Library and Official Modules",
    "releaseDate" : 1492741014417,
    "resolver" : {
      "JCenter" : {
        
      }
    },
    "licenses" : [
      "BSD-3-Clause"
    ],
    "isNonStandardLib" : true,
    "platform" : "jvm",
    "language" : "2.12",
    "fullScalaVersion" : null,
    "scaladocUrl" : null,
    "versionScheme" : null,
    "developers" : [
    ]
  },
  {
    "groupId" : "org.scala-lang",
    "artifactId" : "scalap",
    "version" : "2.12.2",
    "artifactName" : "scalap",
    "projectRef" : {
      "organization" : "scala",
      "repository" : "scala"
    },
    "description" : "bytecode analysis tool",
    "releaseDate" : 1492738164173,
    "resolver" : {
      "JCenter" : {
        
      }
    },
    "licenses" : [
      "BSD-3-Clause"
    ],
    "isNonStandardLib" : true,
    "platform" : "jvm",
    "language" : "2.12",
    "fullScalaVersion" : null,
    "scaladocUrl" : null,
    "versionScheme" : null,
    "developers" : [
    ]
  },
  {
    "groupId" : "org.scala-lang",
    "artifactId" : "scalap",
    "version" : "2.11.11",
    "artifactName" : "scalap",
    "projectRef" : {
      "organization" : "scala",
      "repository" : "scala"
    },
    "description" : "bytecode analysis tool",
    "releaseDate" : 1492586616732,
    "resolver" : {
      "JCenter" : {
        
      }
    },
    "licenses" : [
      "BSD-3-Clause"
    ],
    "isNonStandardLib" : true,
    "platform" : "jvm",
    "language" : "2.11",
    "fullScalaVersion" : null,
    "scaladocUrl" : null,
    "versionScheme" : null,
    "developers" : [
    ]
  },
  {
    "groupId" : "org.scala-lang",
    "artifactId" : "scala-reflect",
    "version" : "2.11.11",
    "artifactName" : "scala-reflect",
    "projectRef" : {
      "organization" : "scala",
      "repository" : "scala"
    },
    "description" : "Compiler for the Scala Programming Language",
    "releaseDate" : 1492529930844,
    "resolver" : {
      "JCenter" : {
        
      }
    },
    "licenses" : [
      "BSD-3-Clause"
    ],
    "isNonStandardLib" : true,
    "platform" : "jvm",
    "language" : "2.11",
    "fullScalaVersion" : null,
    "scaladocUrl" : null,
    "versionScheme" : null,
    "developers" : [
    ]
  },
  {
    "groupId" : "org.scala-lang",
    "artifactId" : "scala-library",
    "version" : "2.11.11",
    "artifactName" : "scala-library",
    "projectRef" : {
      "organization" : "scala",
      "repository" : "scala"
    },
    "description" : "Standard library for the Scala Programming Language",
    "releaseDate" : 1492529927663,
    "resolver" : {
      "JCenter" : {
        
      }
    },
    "licenses" : [
      "BSD-3-Clause"
    ],
    "isNonStandardLib" : true,
    "platform" : "jvm",
    "language" : "2.11",
    "fullScalaVersion" : null,
    "scaladocUrl" : null,
    "versionScheme" : null,
    "developers" : [
    ]
  },
  {
    "groupId" : "org.scala-lang",
    "artifactId" : "scala-compiler",
    "version" : "2.11.11",
    "artifactName" : "scala-compiler",
    "projectRef" : {
      "organization" : "scala",
      "repository" : "scala"
    },
    "description" : "Compiler for the Scala Programming Language",
    "releaseDate" : 1492529924981,
    "resolver" : {
      "JCenter" : {
        
      }
    },
    "licenses" : [
      "BSD-3-Clause"
    ],
    "isNonStandardLib" : true,
    "platform" : "jvm",
    "language" : "2.11",
    "fullScalaVersion" : null,
    "scaladocUrl" : null,
    "versionScheme" : null,
    "developers" : [
    ]
  },
  {
    "groupId" : "org.scala-lang",
    "artifactId" : "scala-reflect",
    "version" : "2.12.2",
    "artifactName" : "scala-reflect",
    "projectRef" : {
      "organization" : "scala",
      "repository" : "scala"
    },
    "description" : "Compiler for the Scala Programming Language",
    "releaseDate" : 1492528639223,
    "resolver" : {
      "JCenter" : {
        
      }
    },
    "licenses" : [
      "BSD-3-Clause"
    ],
    "isNonStandardLib" : true,
    "platform" : "jvm",
    "language" : "2.12",
    "fullScalaVersion" : null,
    "scaladocUrl" : null,
    "versionScheme" : null,
    "developers" : [
    ]
  },
  {
    "groupId" : "org.scala-lang",
    "artifactId" : "scala-compiler",
    "version" : "2.12.2",
    "artifactName" : "scala-compiler",
    "projectRef" : {
      "organization" : "scala",
      "repository" : "scala"
    },
    "description" : "Compiler for the Scala Programming Language",
    "releaseDate" : 1492528631279,
    "resolver" : {
      "JCenter" : {
        
      }
    },
    "licenses" : [
      "BSD-3-Clause"
    ],
    "isNonStandardLib" : true,
    "platform" : "jvm",
    "language" : "2.12",
    "fullScalaVersion" : null,
    "scaladocUrl" : null,
    "versionScheme" : null,
    "developers" : [
    ]
  },
  {
    "groupId" : "org.scala-lang",
    "artifactId" : "scala-library",
    "version" : "2.12.2",
    "artifactName" : "scala-library",
    "projectRef" : {
      "organization" : "scala",
      "repository" : "scala"
    },
    "description" : "Standard library for the Scala Programming Language",
    "releaseDate" : 1492528624219,
    "resolver" : {
      "JCenter" : {
        
      }
    },
    "licenses" : [
      "BSD-3-Clause"
    ],
    "isNonStandardLib" : true,
    "platform" : "jvm",
    "language" : "2.12",
    "fullScalaVersion" : null,
    "scaladocUrl" : null,
    "versionScheme" : null,
    "developers" : [
    ]
  },
  {
    "groupId" : "org.scala-lang",
    "artifactId" : "scalap",
    "version" : "2.11.10",
    "artifactName" : "scalap",
    "projectRef" : {
      "organization" : "scala",
      "repository" : "scala"
    },
    "description" : "bytecode analysis tool",
    "releaseDate" : 1491811872847,
    "resolver" : {
      "JCenter" : {
        
      }
    },
    "licenses" : [
      "BSD-3-Clause"
    ],
    "isNonStandardLib" : true,
    "platform" : "jvm",
    "language" : "2.11",
    "fullScalaVersion" : null,
    "scaladocUrl" : null,
    "versionScheme" : null,
    "developers" : [
    ]
  },
  {
    "groupId" : "org.scala-lang",
    "artifactId" : "scala-reflect",
    "version" : "2.11.10",
    "artifactName" : "scala-reflect",
    "projectRef" : {
      "organization" : "scala",
      "repository" : "scala"
    },
    "description" : "Compiler for the Scala Programming Language",
    "releaseDate" : 1491606351673,
    "resolver" : {
      "JCenter" : {
        
      }
    },
    "licenses" : [
      "BSD-3-Clause"
    ],
    "isNonStandardLib" : true,
    "platform" : "jvm",
    "language" : "2.11",
    "fullScalaVersion" : null,
    "scaladocUrl" : null,
    "versionScheme" : null,
    "developers" : [
    ]
  },
  {
    "groupId" : "org.scala-lang",
    "artifactId" : "scala-library",
    "version" : "2.11.10",
    "artifactName" : "scala-library",
    "projectRef" : {
      "organization" : "scala",
      "repository" : "scala"
    },
    "description" : "Standard library for the Scala Programming Language",
    "releaseDate" : 1491606347510,
    "resolver" : {
      "JCenter" : {
        
      }
    },
    "licenses" : [
      "BSD-3-Clause"
    ],
    "isNonStandardLib" : true,
    "platform" : "jvm",
    "language" : "2.11",
    "fullScalaVersion" : null,
    "scaladocUrl" : null,
    "versionScheme" : null,
    "developers" : [
    ]
  },
  {
    "groupId" : "org.scala-lang",
    "artifactId" : "scala-compiler",
    "version" : "2.11.10",
    "artifactName" : "scala-compiler",
    "projectRef" : {
      "organization" : "scala",
      "repository" : "scala"
    },
    "description" : "Compiler for the Scala Programming Language",
    "releaseDate" : 1491606342725,
    "resolver" : {
      "JCenter" : {
        
      }
    },
    "licenses" : [
      "BSD-3-Clause"
    ],
    "isNonStandardLib" : true,
    "platform" : "jvm",
    "language" : "2.11",
    "fullScalaVersion" : null,
    "scaladocUrl" : null,
    "versionScheme" : null,
    "developers" : [
    ]
  },
  {
    "groupId" : "org.scala-lang",
    "artifactId" : "scala-actors",
    "version" : "2.11.9",
    "artifactName" : "scala-actors",
    "projectRef" : {
      "organization" : "scala",
      "repository" : "scala"
    },
    "description" : "Deprecated Actors Library for Scala",
    "releaseDate" : 1491480524405,
    "resolver" : {
      "JCenter" : {
        
      }
    },
    "licenses" : [
      "BSD-3-Clause"
    ],
    "isNonStandardLib" : true,
    "platform" : "jvm",
    "language" : "2.11",
    "fullScalaVersion" : null,
    "scaladocUrl" : null,
    "versionScheme" : null,
    "developers" : [
    ]
  },
  {
    "groupId" : "org.scala-lang",
    "artifactId" : "scalap",
    "version" : "2.11.9",
    "artifactName" : "scalap",
    "projectRef" : {
      "organization" : "scala",
      "repository" : "scala"
    },
    "description" : "bytecode analysis tool",
    "releaseDate" : 1490810533857,
    "resolver" : {
      "JCenter" : {
        
      }
    },
    "licenses" : [
      "BSD-3-Clause"
    ],
    "isNonStandardLib" : true,
    "platform" : "jvm",
    "language" : "2.11",
    "fullScalaVersion" : null,
    "scaladocUrl" : null,
    "versionScheme" : null,
    "developers" : [
    ]
  },
  {
    "groupId" : "org.scala-lang",
    "artifactId" : "scala-reflect",
    "version" : "2.11.9",
    "artifactName" : "scala-reflect",
    "projectRef" : {
      "organization" : "scala",
      "repository" : "scala"
    },
    "description" : "Compiler for the Scala Programming Language",
    "releaseDate" : 1490719452863,
    "resolver" : {
      "JCenter" : {
        
      }
    },
    "licenses" : [
      "BSD-3-Clause"
    ],
    "isNonStandardLib" : true,
    "platform" : "jvm",
    "language" : "2.11",
    "fullScalaVersion" : null,
    "scaladocUrl" : null,
    "versionScheme" : null,
    "developers" : [
    ]
  },
  {
    "groupId" : "org.scala-lang",
    "artifactId" : "scala-compiler",
    "version" : "2.11.9",
    "artifactName" : "scala-compiler",
    "projectRef" : {
      "organization" : "scala",
      "repository" : "scala"
    },
    "description" : "Compiler for the Scala Programming Language",
    "releaseDate" : 1490719448576,
    "resolver" : {
      "JCenter" : {
        
      }
    },
    "licenses" : [
      "BSD-3-Clause"
    ],
    "isNonStandardLib" : true,
    "platform" : "jvm",
    "language" : "2.11",
    "fullScalaVersion" : null,
    "scaladocUrl" : null,
    "versionScheme" : null,
    "developers" : [
    ]
  },
  {
    "groupId" : "org.scala-lang",
    "artifactId" : "scala-library",
    "version" : "2.11.9",
    "artifactName" : "scala-library",
    "projectRef" : {
      "organization" : "scala",
      "repository" : "scala"
    },
    "description" : "Standard library for the Scala Programming Language",
    "releaseDate" : 1490719443572,
    "resolver" : {
      "JCenter" : {
        
      }
    },
    "licenses" : [
      "BSD-3-Clause"
    ],
    "isNonStandardLib" : true,
    "platform" : "jvm",
    "language" : "2.11",
    "fullScalaVersion" : null,
    "scaladocUrl" : null,
    "versionScheme" : null,
    "developers" : [
    ]
  },
  {
    "groupId" : "org.scala-lang",
    "artifactId" : "scala-dist",
    "version" : "2.12.1",
    "artifactName" : "scala-dist",
    "projectRef" : {
      "organization" : "scala",
      "repository" : "scala"
    },
    "description" : "The Artifacts Distributed with Scala",
    "releaseDate" : 1481639859386,
    "resolver" : {
      "JCenter" : {
        
      }
    },
    "licenses" : [
      "BSD-3-Clause"
    ],
    "isNonStandardLib" : true,
    "platform" : "jvm",
    "language" : "2.12",
    "fullScalaVersion" : null,
    "scaladocUrl" : null,
    "versionScheme" : null,
    "developers" : [
    ]
  },
  {
    "groupId" : "org.scala-lang",
    "artifactId" : "scalap",
    "version" : "2.12.1",
    "artifactName" : "scalap",
    "projectRef" : {
      "organization" : "scala",
      "repository" : "scala"
    },
    "description" : "bytecode analysis tool",
    "releaseDate" : 1481004849007,
    "resolver" : {
      "JCenter" : {
        
      }
    },
    "licenses" : [
      "BSD-3-Clause"
    ],
    "isNonStandardLib" : true,
    "platform" : "jvm",
    "language" : "2.12",
    "fullScalaVersion" : null,
    "scaladocUrl" : null,
    "versionScheme" : null,
    "developers" : [
    ]
  },
  {
    "groupId" : "org.scala-lang",
    "artifactId" : "scala-library-all",
    "version" : "2.12.1",
    "artifactName" : "scala-library-all",
    "projectRef" : {
      "organization" : "scala",
      "repository" : "scala"
    },
    "description" : "The Scala Standard Library and Official Modules",
    "releaseDate" : 1480971972501,
    "resolver" : {
      "JCenter" : {
        
      }
    },
    "licenses" : [
      "BSD-3-Clause"
    ],
    "isNonStandardLib" : true,
    "platform" : "jvm",
    "language" : "2.12",
    "fullScalaVersion" : null,
    "scaladocUrl" : null,
    "versionScheme" : null,
    "developers" : [
    ]
  },
  {
    "groupId" : "org.scala-lang",
    "artifactId" : "scala-reflect",
    "version" : "2.12.1",
    "artifactName" : "scala-reflect",
    "projectRef" : {
      "organization" : "scala",
      "repository" : "scala"
    },
    "description" : "Compiler for the Scala Programming Language",
    "releaseDate" : 1480959747021,
    "resolver" : {
      "JCenter" : {
        
      }
    },
    "licenses" : [
      "BSD-3-Clause"
    ],
    "isNonStandardLib" : true,
    "platform" : "jvm",
    "language" : "2.12",
    "fullScalaVersion" : null,
    "scaladocUrl" : null,
    "versionScheme" : null,
    "developers" : [
    ]
  },
  {
    "groupId" : "org.scala-lang",
    "artifactId" : "scala-compiler",
    "version" : "2.12.1",
    "artifactName" : "scala-compiler",
    "projectRef" : {
      "organization" : "scala",
      "repository" : "scala"
    },
    "description" : "Compiler for the Scala Programming Language",
    "releaseDate" : 1480959742062,
    "resolver" : {
      "JCenter" : {
        
      }
    },
    "licenses" : [
      "BSD-3-Clause"
    ],
    "isNonStandardLib" : true,
    "platform" : "jvm",
    "language" : "2.12",
    "fullScalaVersion" : null,
    "scaladocUrl" : null,
    "versionScheme" : null,
    "developers" : [
    ]
  },
  {
    "groupId" : "org.scala-lang",
    "artifactId" : "scala-library",
    "version" : "2.12.1",
    "artifactName" : "scala-library",
    "projectRef" : {
      "organization" : "scala",
      "repository" : "scala"
    },
    "description" : "Standard library for the Scala Programming Language",
    "releaseDate" : 1480959737173,
    "resolver" : {
      "JCenter" : {
        
      }
    },
    "licenses" : [
      "BSD-3-Clause"
    ],
    "isNonStandardLib" : true,
    "platform" : "jvm",
    "language" : "2.12",
    "fullScalaVersion" : null,
    "scaladocUrl" : null,
    "versionScheme" : null,
    "developers" : [
    ]
  },
  {
    "groupId" : "org.scala-lang",
    "artifactId" : "scala-dist",
    "version" : "2.12.0",
    "artifactName" : "scala-dist",
    "projectRef" : {
      "organization" : "scala",
      "repository" : "scala"
    },
    "description" : "The Artifacts Distributed with Scala",
    "releaseDate" : 1477997913920,
    "resolver" : {
      "JCenter" : {
        
      }
    },
    "licenses" : [
      "BSD-3-Clause"
    ],
    "isNonStandardLib" : true,
    "platform" : "jvm",
    "language" : "2.12",
    "fullScalaVersion" : null,
    "scaladocUrl" : null,
    "versionScheme" : null,
    "developers" : [
    ]
  },
  {
    "groupId" : "org.scala-lang",
    "artifactId" : "scala-library-all",
    "version" : "2.12.0",
    "artifactName" : "scala-library-all",
    "projectRef" : {
      "organization" : "scala",
      "repository" : "scala"
    },
    "description" : "The Scala Standard Library and Official Modules",
    "releaseDate" : 1477842919227,
    "resolver" : {
      "JCenter" : {
        
      }
    },
    "licenses" : [
      "BSD-3-Clause"
    ],
    "isNonStandardLib" : true,
    "platform" : "jvm",
    "language" : "2.12",
    "fullScalaVersion" : null,
    "scaladocUrl" : null,
    "versionScheme" : null,
    "developers" : [
    ]
  },
  {
    "groupId" : "org.scala-lang",
    "artifactId" : "scalap",
    "version" : "2.12.0",
    "artifactName" : "scalap",
    "projectRef" : {
      "organization" : "scala",
      "repository" : "scala"
    },
    "description" : "bytecode analysis tool",
    "releaseDate" : 1477721872890,
    "resolver" : {
      "JCenter" : {
        
      }
    },
    "licenses" : [
      "BSD-3-Clause"
    ],
    "isNonStandardLib" : true,
    "platform" : "jvm",
    "language" : "2.12",
    "fullScalaVersion" : null,
    "scaladocUrl" : null,
    "versionScheme" : null,
    "developers" : [
    ]
  },
  {
    "groupId" : "org.scala-lang",
    "artifactId" : "scala-reflect",
    "version" : "2.12.0",
    "artifactName" : "scala-reflect",
    "projectRef" : {
      "organization" : "scala",
      "repository" : "scala"
    },
    "description" : "Compiler for the Scala Programming Language",
    "releaseDate" : 1477703088742,
    "resolver" : {
      "JCenter" : {
        
      }
    },
    "licenses" : [
      "BSD-3-Clause"
    ],
    "isNonStandardLib" : true,
    "platform" : "jvm",
    "language" : "2.12",
    "fullScalaVersion" : null,
    "scaladocUrl" : null,
    "versionScheme" : null,
    "developers" : [
    ]
  },
  {
    "groupId" : "org.scala-lang",
    "artifactId" : "scala-compiler",
    "version" : "2.12.0",
    "artifactName" : "scala-compiler",
    "projectRef" : {
      "organization" : "scala",
      "repository" : "scala"
    },
    "description" : "Compiler for the Scala Programming Language",
    "releaseDate" : 1477703082219,
    "resolver" : {
      "JCenter" : {
        
      }
    },
    "licenses" : [
      "BSD-3-Clause"
    ],
    "isNonStandardLib" : true,
    "platform" : "jvm",
    "language" : "2.12",
    "fullScalaVersion" : null,
    "scaladocUrl" : null,
    "versionScheme" : null,
    "developers" : [
    ]
  },
  {
    "groupId" : "org.scala-lang",
    "artifactId" : "scala-library",
    "version" : "2.12.0",
    "artifactName" : "scala-library",
    "projectRef" : {
      "organization" : "scala",
      "repository" : "scala"
    },
    "description" : "Standard library for the Scala Programming Language",
    "releaseDate" : 1477703076162,
    "resolver" : {
      "JCenter" : {
        
      }
    },
    "licenses" : [
      "BSD-3-Clause"
    ],
    "isNonStandardLib" : true,
    "platform" : "jvm",
    "language" : "2.12",
    "fullScalaVersion" : null,
    "scaladocUrl" : null,
    "versionScheme" : null,
    "developers" : [
    ]
  },
  {
    "groupId" : "org.scala-lang",
    "artifactId" : "scala-dist",
    "version" : "2.11.8",
    "artifactName" : "scala-dist",
    "projectRef" : {
      "organization" : "scala",
      "repository" : "scala"
    },
    "description" : "The Artifacts Distributed with Scala",
    "releaseDate" : 1458743493380,
    "resolver" : {
      "JCenter" : {
        
      }
    },
    "licenses" : [
      "BSD-3-Clause"
    ],
    "isNonStandardLib" : true,
    "platform" : "jvm",
    "language" : "2.11",
    "fullScalaVersion" : null,
    "scaladocUrl" : null,
    "versionScheme" : null,
    "developers" : [
    ]
  },
  {
    "groupId" : "org.scala-lang",
    "artifactId" : "scala-actors",
    "version" : "2.11.8",
    "artifactName" : "scala-actors",
    "projectRef" : {
      "organization" : "scala",
      "repository" : "scala"
    },
    "description" : "Deprecated Actors Library for Scala",
    "releaseDate" : 1457502952715,
    "resolver" : {
      "JCenter" : {
        
      }
    },
    "licenses" : [
      "BSD-3-Clause"
    ],
    "isNonStandardLib" : true,
    "platform" : "jvm",
    "language" : "2.11",
    "fullScalaVersion" : null,
    "scaladocUrl" : null,
    "versionScheme" : null,
    "developers" : [
    ]
  },
  {
    "groupId" : "org.scala-lang",
    "artifactId" : "scalap",
    "version" : "2.11.8",
    "artifactName" : "scalap",
    "projectRef" : {
      "organization" : "scala",
      "repository" : "scala"
    },
    "description" : "bytecode analysis tool",
    "releaseDate" : 1457499611955,
    "resolver" : {
      "JCenter" : {
        
      }
    },
    "licenses" : [
      "BSD-3-Clause"
    ],
    "isNonStandardLib" : true,
    "platform" : "jvm",
    "language" : "2.11",
    "fullScalaVersion" : null,
    "scaladocUrl" : null,
    "versionScheme" : null,
    "developers" : [
    ]
  },
  {
    "groupId" : "org.scala-lang",
    "artifactId" : "scala-library",
    "version" : "2.11.8",
    "artifactName" : "scala-library",
    "projectRef" : {
      "organization" : "scala",
      "repository" : "scala"
    },
    "description" : "Standard library for the Scala Programming Language",
    "releaseDate" : 1457496951828,
    "resolver" : {
      "JCenter" : {
        
      }
    },
    "licenses" : [
      "BSD-3-Clause"
    ],
    "isNonStandardLib" : true,
    "platform" : "jvm",
    "language" : "2.11",
    "fullScalaVersion" : null,
    "scaladocUrl" : null,
    "versionScheme" : null,
    "developers" : [
    ]
  },
  {
    "groupId" : "org.scala-lang",
    "artifactId" : "scalap",
    "version" : "2.10.6",
    "artifactName" : "scalap",
    "projectRef" : {
      "organization" : "scala",
      "repository" : "scala"
    },
    "description" : "bytecode analysis tool",
    "releaseDate" : 1443552612931,
    "resolver" : {
      "JCenter" : {
        
      }
    },
    "licenses" : [
      "BSD-3-Clause"
    ],
    "isNonStandardLib" : true,
    "platform" : "jvm",
    "language" : "2.10",
    "fullScalaVersion" : null,
    "scaladocUrl" : null,
    "versionScheme" : null,
    "developers" : [
    ]
  },
  {
    "groupId" : "org.scala-lang",
    "artifactId" : "scala-reflect",
    "version" : "2.10.6",
    "artifactName" : "scala-reflect",
    "projectRef" : {
      "organization" : "scala",
      "repository" : "scala"
    },
    "description" : "Compiler for the Scala Programming Language",
    "releaseDate" : 1442919758619,
    "resolver" : {
      "JCenter" : {
        
      }
    },
    "licenses" : [
      "BSD-3-Clause"
    ],
    "isNonStandardLib" : true,
    "platform" : "jvm",
    "language" : "2.10",
    "fullScalaVersion" : null,
    "scaladocUrl" : null,
    "versionScheme" : null,
    "developers" : [
    ]
  },
  {
    "groupId" : "org.scala-lang",
    "artifactId" : "scala-library",
    "version" : "2.10.6",
    "artifactName" : "scala-library",
    "projectRef" : {
      "organization" : "scala",
      "repository" : "scala"
    },
    "description" : "Standard library for the Scala Programming Language",
    "releaseDate" : 1442919757210,
    "resolver" : {
      "JCenter" : {
        
      }
    },
    "licenses" : [
      "BSD-3-Clause"
    ],
    "isNonStandardLib" : true,
    "platform" : "jvm",
    "language" : "2.10",
    "fullScalaVersion" : null,
    "scaladocUrl" : null,
    "versionScheme" : null,
    "developers" : [
    ]
  },
  {
    "groupId" : "org.scala-lang",
    "artifactId" : "scala-actors",
    "version" : "2.11.7",
    "artifactName" : "scala-actors",
    "projectRef" : {
      "organization" : "scala",
      "repository" : "scala"
    },
    "description" : "Deprecated Actors Library for Scala",
    "releaseDate" : 1436026935626,
    "resolver" : {
      "JCenter" : {
        
      }
    },
    "licenses" : [
      "BSD-3-Clause"
    ],
    "isNonStandardLib" : true,
    "platform" : "jvm",
    "language" : "2.11",
    "fullScalaVersion" : null,
    "scaladocUrl" : null,
    "versionScheme" : null,
    "developers" : [
    ]
  },
  {
    "groupId" : "org.scala-lang",
    "artifactId" : "scala-dist",
    "version" : "2.11.7",
    "artifactName" : "scala-dist",
    "projectRef" : {
      "organization" : "scala",
      "repository" : "scala"
    },
    "description" : "The Artifacts Distributed with Scala",
    "releaseDate" : 1435759781454,
    "resolver" : {
      "JCenter" : {
        
      }
    },
    "licenses" : [
      "BSD-3-Clause"
    ],
    "isNonStandardLib" : true,
    "platform" : "jvm",
    "language" : "2.11",
    "fullScalaVersion" : null,
    "scaladocUrl" : null,
    "versionScheme" : null,
    "developers" : [
    ]
  },
  {
    "groupId" : "org.scala-lang",
    "artifactId" : "scalap",
    "version" : "2.11.7",
    "artifactName" : "scalap",
    "projectRef" : {
      "organization" : "scala",
      "repository" : "scala"
    },
    "description" : "bytecode analysis tool",
    "releaseDate" : 1435217392378,
    "resolver" : {
      "JCenter" : {
        
      }
    },
    "licenses" : [
      "BSD-3-Clause"
    ],
    "isNonStandardLib" : true,
    "platform" : "jvm",
    "language" : "2.11",
    "fullScalaVersion" : null,
    "scaladocUrl" : null,
    "versionScheme" : null,
    "developers" : [
    ]
  },
  {
    "groupId" : "org.scala-lang",
    "artifactId" : "scala-reflect",
    "version" : "2.11.7",
    "artifactName" : "scala-reflect",
    "projectRef" : {
      "organization" : "scala",
      "repository" : "scala"
    },
    "description" : "Compiler for the Scala Programming Language",
    "releaseDate" : 1435105128877,
    "resolver" : {
      "JCenter" : {
        
      }
    },
    "licenses" : [
      "BSD-3-Clause"
    ],
    "isNonStandardLib" : true,
    "platform" : "jvm",
    "language" : "2.11",
    "fullScalaVersion" : null,
    "scaladocUrl" : null,
    "versionScheme" : null,
    "developers" : [
    ]
  },
  {
    "groupId" : "org.scala-lang",
    "artifactId" : "scala-compiler",
    "version" : "2.11.7",
    "artifactName" : "scala-compiler",
    "projectRef" : {
      "organization" : "scala",
      "repository" : "scala"
    },
    "description" : "Compiler for the Scala Programming Language",
    "releaseDate" : 1435105128714,
    "resolver" : {
      "JCenter" : {
        
      }
    },
    "licenses" : [
      "BSD-3-Clause"
    ],
    "isNonStandardLib" : true,
    "platform" : "jvm",
    "language" : "2.11",
    "fullScalaVersion" : null,
    "scaladocUrl" : null,
    "versionScheme" : null,
    "developers" : [
    ]
  },
  {
    "groupId" : "org.scala-lang",
    "artifactId" : "scala-actors",
    "version" : "2.11.6",
    "artifactName" : "scala-actors",
    "projectRef" : {
      "organization" : "scala",
      "repository" : "scala"
    },
    "description" : "Deprecated Actors Library for Scala",
    "releaseDate" : 1425812568363,
    "resolver" : {
      "JCenter" : {
        
      }
    },
    "licenses" : [
      "BSD-3-Clause"
    ],
    "isNonStandardLib" : true,
    "platform" : "jvm",
    "language" : "2.11",
    "fullScalaVersion" : null,
    "scaladocUrl" : null,
    "versionScheme" : null,
    "developers" : [
    ]
  },
  {
    "groupId" : "org.scala-lang",
    "artifactId" : "scalap",
    "version" : "2.10.5",
    "artifactName" : "scalap",
    "projectRef" : {
      "organization" : "scala",
      "repository" : "scala"
    },
    "description" : "bytecode analysis tool",
    "releaseDate" : 1425713074118,
    "resolver" : {
      "JCenter" : {
        
      }
    },
    "licenses" : [
      "BSD-3-Clause"
    ],
    "isNonStandardLib" : true,
    "platform" : "jvm",
    "language" : "2.10",
    "fullScalaVersion" : null,
    "scaladocUrl" : null,
    "versionScheme" : null,
    "developers" : [
    ]
  },
  {
    "groupId" : "org.scala-lang",
    "artifactId" : "scala-actors",
    "version" : "2.10.5",
    "artifactName" : "scala-actors",
    "projectRef" : {
      "organization" : "scala",
      "repository" : "scala"
    },
    "description" : "Deprecated Actors Library for Scala",
    "releaseDate" : 1425712953344,
    "resolver" : {
      "JCenter" : {
        
      }
    },
    "licenses" : [
      "BSD-3-Clause"
    ],
    "isNonStandardLib" : true,
    "platform" : "jvm",
    "language" : "2.10",
    "fullScalaVersion" : null,
    "scaladocUrl" : null,
    "versionScheme" : null,
    "developers" : [
    ]
  },
  {
    "groupId" : "org.scala-lang",
    "artifactId" : "scala-compiler",
    "version" : "2.10.5",
    "artifactName" : "scala-compiler",
    "projectRef" : {
      "organization" : "scala",
      "repository" : "scala"
    },
    "description" : "Compiler for the Scala Programming Language",
    "releaseDate" : 1425540630049,
    "resolver" : {
      "JCenter" : {
        
      }
    },
    "licenses" : [
      "BSD-3-Clause"
    ],
    "isNonStandardLib" : true,
    "platform" : "jvm",
    "language" : "2.10",
    "fullScalaVersion" : null,
    "scaladocUrl" : null,
    "versionScheme" : null,
    "developers" : [
    ]
  },
  {
    "groupId" : "org.scala-lang",
    "artifactId" : "scala-library",
    "version" : "2.10.5",
    "artifactName" : "scala-library",
    "projectRef" : {
      "organization" : "scala",
      "repository" : "scala"
    },
    "description" : "Standard library for the Scala Programming Language",
    "releaseDate" : 1425520378119,
    "resolver" : {
      "JCenter" : {
        
      }
    },
    "licenses" : [
      "BSD-3-Clause"
    ],
    "isNonStandardLib" : true,
    "platform" : "jvm",
    "language" : "2.10",
    "fullScalaVersion" : null,
    "scaladocUrl" : null,
    "versionScheme" : null,
    "developers" : [
    ]
  },
  {
    "groupId" : "org.scala-lang",
    "artifactId" : "scalap",
    "version" : "2.11.6",
    "artifactName" : "scalap",
    "projectRef" : {
      "organization" : "scala",
      "repository" : "scala"
    },
    "description" : "bytecode analysis tool",
    "releaseDate" : 1425456990340,
    "resolver" : {
      "JCenter" : {
        
      }
    },
    "licenses" : [
      "BSD-3-Clause"
    ],
    "isNonStandardLib" : true,
    "platform" : "jvm",
    "language" : "2.11",
    "fullScalaVersion" : null,
    "scaladocUrl" : null,
    "versionScheme" : null,
    "developers" : [
    ]
  },
  {
    "groupId" : "org.scala-lang",
    "artifactId" : "scala-dist",
    "version" : "2.11.6",
    "artifactName" : "scala-dist",
    "projectRef" : {
      "organization" : "scala",
      "repository" : "scala"
    },
    "description" : "The Artifacts Distributed with Scala",
    "releaseDate" : 1425456621963,
    "resolver" : {
      "JCenter" : {
        
      }
    },
    "licenses" : [
      "BSD-3-Clause"
    ],
    "isNonStandardLib" : true,
    "platform" : "jvm",
    "language" : "2.11",
    "fullScalaVersion" : null,
    "scaladocUrl" : null,
    "versionScheme" : null,
    "developers" : [
    ]
  },
  {
    "groupId" : "org.scala-lang",
    "artifactId" : "scala-compiler",
    "version" : "2.11.6",
    "artifactName" : "scala-compiler",
    "projectRef" : {
      "organization" : "scala",
      "repository" : "scala"
    },
    "description" : "Compiler for the Scala Programming Language",
    "releaseDate" : 1425390774918,
    "resolver" : {
      "JCenter" : {
        
      }
    },
    "licenses" : [
      "BSD-3-Clause"
    ],
    "isNonStandardLib" : true,
    "platform" : "jvm",
    "language" : "2.11",
    "fullScalaVersion" : null,
    "scaladocUrl" : null,
    "versionScheme" : null,
    "developers" : [
    ]
  },
  {
    "groupId" : "org.scala-lang",
    "artifactId" : "scala-library",
    "version" : "2.11.6",
    "artifactName" : "scala-library",
    "projectRef" : {
      "organization" : "scala",
      "repository" : "scala"
    },
    "description" : "Standard library for the Scala Programming Language",
    "releaseDate" : 1425336914225,
    "resolver" : {
      "JCenter" : {
        
      }
    },
    "licenses" : [
      "BSD-3-Clause"
    ],
    "isNonStandardLib" : true,
    "platform" : "jvm",
    "language" : "2.11",
    "fullScalaVersion" : null,
    "scaladocUrl" : null,
    "versionScheme" : null,
    "developers" : [
    ]
  },
  {
    "groupId" : "org.scala-lang",
    "artifactId" : "scala-actors",
    "version" : "2.11.5",
    "artifactName" : "scala-actors",
    "projectRef" : {
      "organization" : "scala",
      "repository" : "scala"
    },
    "description" : "Deprecated Actors Library for Scala",
    "releaseDate" : 1421055818857,
    "resolver" : {
      "JCenter" : {
        
      }
    },
    "licenses" : [
      "BSD-3-Clause"
    ],
    "isNonStandardLib" : true,
    "platform" : "jvm",
    "language" : "2.11",
    "fullScalaVersion" : null,
    "scaladocUrl" : null,
    "versionScheme" : null,
    "developers" : [
    ]
  },
  {
    "groupId" : "org.scala-lang",
    "artifactId" : "scala-dist",
    "version" : "2.11.5",
    "artifactName" : "scala-dist",
    "projectRef" : {
      "organization" : "scala",
      "repository" : "scala"
    },
    "description" : "The Artifacts Distributed with Scala",
    "releaseDate" : 1420835057136,
    "resolver" : {
      "JCenter" : {
        
      }
    },
    "licenses" : [
      "BSD-3-Clause"
    ],
    "isNonStandardLib" : true,
    "platform" : "jvm",
    "language" : "2.11",
    "fullScalaVersion" : null,
    "scaladocUrl" : null,
    "versionScheme" : null,
    "developers" : [
    ]
  },
  {
    "groupId" : "org.scala-lang",
    "artifactId" : "scalap",
    "version" : "2.11.5",
    "artifactName" : "scalap",
    "projectRef" : {
      "organization" : "scala",
      "repository" : "scala"
    },
    "description" : "bytecode analysis tool",
    "releaseDate" : 1420760436692,
    "resolver" : {
      "JCenter" : {
        
      }
    },
    "licenses" : [
      "BSD-3-Clause"
    ],
    "isNonStandardLib" : true,
    "platform" : "jvm",
    "language" : "2.11",
    "fullScalaVersion" : null,
    "scaladocUrl" : null,
    "versionScheme" : null,
    "developers" : [
    ]
  },
  {
    "groupId" : "org.scala-lang",
    "artifactId" : "scala-library",
    "version" : "2.11.5",
    "artifactName" : "scala-library",
    "projectRef" : {
      "organization" : "scala",
      "repository" : "scala"
    },
    "description" : "Standard library for the Scala Programming Language",
    "releaseDate" : 1420711302857,
    "resolver" : {
      "JCenter" : {
        
      }
    },
    "licenses" : [
      "BSD-3-Clause"
    ],
    "isNonStandardLib" : true,
    "platform" : "jvm",
    "language" : "2.11",
    "fullScalaVersion" : null,
    "scaladocUrl" : null,
    "versionScheme" : null,
    "developers" : [
    ]
  },
  {
    "groupId" : "org.scala-lang",
    "artifactId" : "scala-dist",
    "version" : "2.11.3",
    "artifactName" : "scala-dist",
    "projectRef" : {
      "organization" : "scala",
      "repository" : "scala"
    },
    "description" : "The Artifacts Distributed with Scala",
    "releaseDate" : 1418921618400,
    "resolver" : {
      "JCenter" : {
        
      }
    },
    "licenses" : [
      "BSD-3-Clause"
    ],
    "isNonStandardLib" : true,
    "platform" : "jvm",
    "language" : "2.11",
    "fullScalaVersion" : null,
    "scaladocUrl" : null,
    "versionScheme" : null,
    "developers" : [
    ]
  },
  {
    "groupId" : "org.scala-lang",
    "artifactId" : "scala-dist",
    "version" : "2.11.4",
    "artifactName" : "scala-dist",
    "projectRef" : {
      "organization" : "scala",
      "repository" : "scala"
    },
    "description" : "The Artifacts Distributed with Scala",
    "releaseDate" : 1415862649590,
    "resolver" : {
      "JCenter" : {
        
      }
    },
    "licenses" : [
      "BSD-3-Clause"
    ],
    "isNonStandardLib" : true,
    "platform" : "jvm",
    "language" : "2.11",
    "fullScalaVersion" : null,
    "scaladocUrl" : null,
    "versionScheme" : null,
    "developers" : [
    ]
  },
  {
    "groupId" : "org.scala-lang",
    "artifactId" : "scalap",
    "version" : "2.11.4",
    "artifactName" : "scalap",
    "projectRef" : {
      "organization" : "scala",
      "repository" : "scala"
    },
    "description" : "bytecode analysis tool",
    "releaseDate" : 1414630135945,
    "resolver" : {
      "JCenter" : {
        
      }
    },
    "licenses" : [
      "BSD-3-Clause"
    ],
    "isNonStandardLib" : true,
    "platform" : "jvm",
    "language" : "2.11",
    "fullScalaVersion" : null,
    "scaladocUrl" : null,
    "versionScheme" : null,
    "developers" : [
    ]
  },
  {
    "groupId" : "org.scala-lang",
    "artifactId" : "scala-compiler",
    "version" : "2.11.4",
    "artifactName" : "scala-compiler",
    "projectRef" : {
      "organization" : "scala",
      "repository" : "scala"
    },
    "description" : "Compiler for the Scala Programming Language",
    "releaseDate" : 1414543725258,
    "resolver" : {
      "JCenter" : {
        
      }
    },
    "licenses" : [
      "BSD-3-Clause"
    ],
    "isNonStandardLib" : true,
    "platform" : "jvm",
    "language" : "2.11",
    "fullScalaVersion" : null,
    "scaladocUrl" : null,
    "versionScheme" : null,
    "developers" : [
    ]
  },
  {
    "groupId" : "org.scala-lang",
    "artifactId" : "scala-library",
    "version" : "2.11.4",
    "artifactName" : "scala-library",
    "projectRef" : {
      "organization" : "scala",
      "repository" : "scala"
    },
    "description" : "Standard library for the Scala Programming Language",
    "releaseDate" : 1414525695080,
    "resolver" : {
      "JCenter" : {
        
      }
    },
    "licenses" : [
      "BSD-3-Clause"
    ],
    "isNonStandardLib" : true,
    "platform" : "jvm",
    "language" : "2.11",
    "fullScalaVersion" : null,
    "scaladocUrl" : null,
    "versionScheme" : null,
    "developers" : [
    ]
  },
  {
    "groupId" : "org.scala-lang",
    "artifactId" : "scalap",
    "version" : "2.11.3",
    "artifactName" : "scalap",
    "projectRef" : {
      "organization" : "scala",
      "repository" : "scala"
    },
    "description" : "bytecode analysis tool",
    "releaseDate" : 1413352941171,
    "resolver" : {
      "JCenter" : {
        
      }
    },
    "licenses" : [
      "BSD-3-Clause"
    ],
    "isNonStandardLib" : true,
    "platform" : "jvm",
    "language" : "2.11",
    "fullScalaVersion" : null,
    "scaladocUrl" : null,
    "versionScheme" : null,
    "developers" : [
    ]
  },
  {
    "groupId" : "org.scala-lang",
    "artifactId" : "scala-compiler",
    "version" : "2.11.3",
    "artifactName" : "scala-compiler",
    "projectRef" : {
      "organization" : "scala",
      "repository" : "scala"
    },
    "description" : "Compiler for the Scala Programming Language",
    "releaseDate" : 1412995274363,
    "resolver" : {
      "JCenter" : {
        
      }
    },
    "licenses" : [
      "BSD-3-Clause"
    ],
    "isNonStandardLib" : true,
    "platform" : "jvm",
    "language" : "2.11",
    "fullScalaVersion" : null,
    "scaladocUrl" : null,
    "versionScheme" : null,
    "developers" : [
    ]
  },
  {
    "groupId" : "org.scala-lang",
    "artifactId" : "scala-reflect",
    "version" : "2.11.3",
    "artifactName" : "scala-reflect",
    "projectRef" : {
      "organization" : "scala",
      "repository" : "scala"
    },
    "description" : "Compiler for the Scala Programming Language",
    "releaseDate" : 1412995124613,
    "resolver" : {
      "JCenter" : {
        
      }
    },
    "licenses" : [
      "BSD-3-Clause"
    ],
    "isNonStandardLib" : true,
    "platform" : "jvm",
    "language" : "2.11",
    "fullScalaVersion" : null,
    "scaladocUrl" : null,
    "versionScheme" : null,
    "developers" : [
    ]
  },
  {
    "groupId" : "org.scala-lang",
    "artifactId" : "scala-library",
    "version" : "2.11.3",
    "artifactName" : "scala-library",
    "projectRef" : {
      "organization" : "scala",
      "repository" : "scala"
    },
    "description" : "Standard library for the Scala Programming Language",
    "releaseDate" : 1412988651530,
    "resolver" : {
      "JCenter" : {
        
      }
    },
    "licenses" : [
      "BSD-3-Clause"
    ],
    "isNonStandardLib" : true,
    "platform" : "jvm",
    "language" : "2.11",
    "fullScalaVersion" : null,
    "scaladocUrl" : null,
    "versionScheme" : null,
    "developers" : [
    ]
  },
  {
    "groupId" : "org.scala-lang",
    "artifactId" : "scala-dist",
    "version" : "2.11.2",
    "artifactName" : "scala-dist",
    "projectRef" : {
      "organization" : "scala",
      "repository" : "scala"
    },
    "description" : "The Artifacts Distributed with Scala",
    "releaseDate" : 1406450452110,
    "resolver" : {
      "JCenter" : {
        
      }
    },
    "licenses" : [
      "BSD-3-Clause"
    ],
    "isNonStandardLib" : true,
    "platform" : "jvm",
    "language" : "2.11",
    "fullScalaVersion" : null,
    "scaladocUrl" : null,
    "versionScheme" : null,
    "developers" : [
    ]
  },
  {
    "groupId" : "org.scala-lang",
    "artifactId" : "scalap",
    "version" : "2.11.2",
    "artifactName" : "scalap",
    "projectRef" : {
      "organization" : "scala",
      "repository" : "scala"
    },
    "description" : "bytecode analysis tool",
    "releaseDate" : 1406291275593,
    "resolver" : {
      "JCenter" : {
        
      }
    },
    "licenses" : [
      "BSD-3-Clause"
    ],
    "isNonStandardLib" : true,
    "platform" : "jvm",
    "language" : "2.11",
    "fullScalaVersion" : null,
    "scaladocUrl" : null,
    "versionScheme" : null,
    "developers" : [
    ]
  },
  {
    "groupId" : "org.scala-lang",
    "artifactId" : "scala-reflect",
    "version" : "2.11.2",
    "artifactName" : "scala-reflect",
    "projectRef" : {
      "organization" : "scala",
      "repository" : "scala"
    },
    "description" : "Compiler for the Scala Programming Language",
    "releaseDate" : 1406120620899,
    "resolver" : {
      "JCenter" : {
        
      }
    },
    "licenses" : [
      "BSD-3-Clause"
    ],
    "isNonStandardLib" : true,
    "platform" : "jvm",
    "language" : "2.11",
    "fullScalaVersion" : null,
    "scaladocUrl" : null,
    "versionScheme" : null,
    "developers" : [
    ]
  },
  {
    "groupId" : "org.scala-lang",
    "artifactId" : "scala-compiler",
    "version" : "2.11.2",
    "artifactName" : "scala-compiler",
    "projectRef" : {
      "organization" : "scala",
      "repository" : "scala"
    },
    "description" : "Compiler for the Scala Programming Language",
    "releaseDate" : 1406120580434,
    "resolver" : {
      "JCenter" : {
        
      }
    },
    "licenses" : [
      "BSD-3-Clause"
    ],
    "isNonStandardLib" : true,
    "platform" : "jvm",
    "language" : "2.11",
    "fullScalaVersion" : null,
    "scaladocUrl" : null,
    "versionScheme" : null,
    "developers" : [
    ]
  },
  {
    "groupId" : "org.scala-lang",
    "artifactId" : "scala-library",
    "version" : "2.11.2",
    "artifactName" : "scala-library",
    "projectRef" : {
      "organization" : "scala",
      "repository" : "scala"
    },
    "description" : "Standard library for the Scala Programming Language",
    "releaseDate" : 1406120574885,
    "resolver" : {
      "JCenter" : {
        
      }
    },
    "licenses" : [
      "BSD-3-Clause"
    ],
    "isNonStandardLib" : true,
    "platform" : "jvm",
    "language" : "2.11",
    "fullScalaVersion" : null,
    "scaladocUrl" : null,
    "versionScheme" : null,
    "developers" : [
    ]
  }
]