[
  {
    "source" : {
      "groupId" : "org.scalanlp",
      "artifactId" : "nak_2.10",
      "version" : "1.3"
    },
    "target" : {
      "groupId" : "com.typesafe.scala-logging",
      "artifactId" : "scala-logging-slf4j_2.10",
      "version" : "2.1.2"
    },
    "scope" : "compile"
  },
  {
    "source" : {
      "groupId" : "org.scalanlp",
      "artifactId" : "nak_2.10",
      "version" : "1.3"
    },
    "target" : {
      "groupId" : "org.apache.logging.log4j",
      "artifactId" : "log4j-core",
      "version" : "2.0-beta8"
    },
    "scope" : "runtime"
  },
  {
    "source" : {
      "groupId" : "org.scalanlp",
      "artifactId" : "nak_2.10",
      "version" : "1.3"
    },
    "target" : {
      "groupId" : "org.rogach",
      "artifactId" : "scallop_2.10",
      "version" : "0.9.5"
    },
    "scope" : "compile"
  },
  {
    "source" : {
      "groupId" : "org.scalanlp",
      "artifactId" : "nak_2.10",
      "version" : "1.3"
    },
    "target" : {
      "groupId" : "org.scalacheck",
      "artifactId" : "scalacheck_2.10",
      "version" : "1.11.3"
    },
    "scope" : "test"
  },
  {
    "source" : {
      "groupId" : "org.scalanlp",
      "artifactId" : "nak_2.10",
      "version" : "1.3"
    },
    "target" : {
      "groupId" : "org.scala-lang",
      "artifactId" : "scala-library",
      "version" : "2.10.4"
    },
    "scope" : "compile"
  },
  {
    "source" : {
      "groupId" : "org.scalanlp",
      "artifactId" : "nak_2.10",
      "version" : "1.3"
    },
    "target" : {
      "groupId" : "org.scalanlp",
      "artifactId" : "breeze_2.10",
      "version" : "0.9"
    },
    "scope" : "compile"
  },
  {
    "source" : {
      "groupId" : "org.scalanlp",
      "artifactId" : "nak_2.10",
      "version" : "1.3"
    },
    "target" : {
      "groupId" : "org.scalanlp",
      "artifactId" : "breeze-config_2.10",
      "version" : "0.9.1"
    },
    "scope" : "compile"
  },
  {
    "source" : {
      "groupId" : "org.scalanlp",
      "artifactId" : "nak_2.10",
      "version" : "1.3"
    },
    "target" : {
      "groupId" : "org.scalanlp",
      "artifactId" : "breeze-natives_2.10",
      "version" : "0.8"
    },
    "scope" : "runtime"
  },
  {
    "source" : {
      "groupId" : "org.scalanlp",
      "artifactId" : "nak_2.10",
      "version" : "1.3"
    },
    "target" : {
      "groupId" : "org.scalatest",
      "artifactId" : "scalatest_2.10",
      "version" : "2.1.3"
    },
    "scope" : "test"
  },
  {
    "source" : {
      "groupId" : "org.scalanlp",
      "artifactId" : "nak_2.11",
      "version" : "1.3.2"
    },
    "target" : {
      "groupId" : "com.typesafe.scala-logging",
      "artifactId" : "scala-logging_2.11",
      "version" : "3.3.0"
    },
    "scope" : "compile"
  },
  {
    "source" : {
      "groupId" : "org.scalanlp",
      "artifactId" : "nak_2.11",
      "version" : "1.3.2"
    },
    "target" : {
      "groupId" : "org.apache.logging.log4j",
      "artifactId" : "log4j-core",
      "version" : "2.4.1"
    },
    "scope" : "runtime"
  },
  {
    "source" : {
      "groupId" : "org.scalanlp",
      "artifactId" : "nak_2.11",
      "version" : "1.3.2"
    },
    "target" : {
      "groupId" : "org.rogach",
      "artifactId" : "scallop_2.11",
      "version" : "0.9.5"
    },
    "scope" : "compile"
  },
  {
    "source" : {
      "groupId" : "org.scalanlp",
      "artifactId" : "nak_2.11",
      "version" : "1.3.2"
    },
    "target" : {
      "groupId" : "org.scalacheck",
      "artifactId" : "scalacheck_2.11",
      "version" : "1.11.3"
    },
    "scope" : "test"
  },
  {
    "source" : {
      "groupId" : "org.scalanlp",
      "artifactId" : "nak_2.11",
      "version" : "1.3.2"
    },
    "target" : {
      "groupId" : "org.scala-lang",
      "artifactId" : "scala-library",
      "version" : "2.11.8"
    },
    "scope" : "compile"
  },
  {
    "source" : {
      "groupId" : "org.scalanlp",
      "artifactId" : "nak_2.11",
      "version" : "1.3.2"
    },
    "target" : {
      "groupId" : "org.scalanlp",
      "artifactId" : "breeze_2.11",
      "version" : "0.9"
    },
    "scope" : "compile"
  },
  {
    "source" : {
      "groupId" : "org.scalanlp",
      "artifactId" : "nak_2.11",
      "version" : "1.3.2"
    },
    "target" : {
      "groupId" : "org.scalanlp",
      "artifactId" : "breeze-config_2.11",
      "version" : "0.9.1"
    },
    "scope" : "compile"
  },
  {
    "source" : {
      "groupId" : "org.scalanlp",
      "artifactId" : "nak_2.11",
      "version" : "1.3.2"
    },
    "target" : {
      "groupId" : "org.scalanlp",
      "artifactId" : "breeze-natives_2.11",
      "version" : "0.8"
    },
    "scope" : "runtime"
  },
  {
    "source" : {
      "groupId" : "org.scalanlp",
      "artifactId" : "nak_2.11",
      "version" : "1.3.2"
    },
    "target" : {
      "groupId" : "org.scalatest",
      "artifactId" : "scalatest_2.11",
      "version" : "2.1.3"
    },
    "scope" : "test"
  },
  {
    "source" : {
      "groupId" : "org.scalanlp",
      "artifactId" : "nak_2.10",
      "version" : "1.2.1"
    },
    "target" : {
      "groupId" : "com.typesafe",
      "artifactId" : "scalalogging-log4j_2.10",
      "version" : "1.0.1"
    },
    "scope" : "compile"
  },
  {
    "source" : {
      "groupId" : "org.scalanlp",
      "artifactId" : "nak_2.10",
      "version" : "1.2.1"
    },
    "target" : {
      "groupId" : "com.typesafe.sbt",
      "artifactId" : "sbt-pgp",
      "version" : "0.8.3"
    },
    "scope" : "compile"
  },
  {
    "source" : {
      "groupId" : "org.scalanlp",
      "artifactId" : "nak_2.10",
      "version" : "1.2.1"
    },
    "target" : {
      "groupId" : "org.apache.logging.log4j",
      "artifactId" : "log4j-core",
      "version" : "2.0-beta8"
    },
    "scope" : "compile"
  },
  {
    "source" : {
      "groupId" : "org.scalanlp",
      "artifactId" : "nak_2.10",
      "version" : "1.2.1"
    },
    "target" : {
      "groupId" : "org.rogach",
      "artifactId" : "scallop_2.10",
      "version" : "0.9.4"
    },
    "scope" : "compile"
  },
  {
    "source" : {
      "groupId" : "org.scalanlp",
      "artifactId" : "nak_2.10",
      "version" : "1.2.1"
    },
    "target" : {
      "groupId" : "org.scalacheck",
      "artifactId" : "scalacheck_2.10",
      "version" : "1.10.0"
    },
    "scope" : "test"
  },
  {
    "source" : {
      "groupId" : "org.scalanlp",
      "artifactId" : "nak_2.10",
      "version" : "1.2.1"
    },
    "target" : {
      "groupId" : "org.scala-lang",
      "artifactId" : "scala-library",
      "version" : "2.10.3"
    },
    "scope" : "compile"
  },
  {
    "source" : {
      "groupId" : "org.scalanlp",
      "artifactId" : "nak_2.10",
      "version" : "1.2.1"
    },
    "target" : {
      "groupId" : "org.scalanlp",
      "artifactId" : "breeze_2.10",
      "version" : "0.8.1"
    },
    "scope" : "compile"
  },
  {
    "source" : {
      "groupId" : "org.scalanlp",
      "artifactId" : "nak_2.10",
      "version" : "1.2.1"
    },
    "target" : {
      "groupId" : "org.scalanlp",
      "artifactId" : "breeze-config_2.10",
      "version" : "0.8"
    },
    "scope" : "compile"
  },
  {
    "source" : {
      "groupId" : "org.scalanlp",
      "artifactId" : "nak_2.10",
      "version" : "1.2.1"
    },
    "target" : {
      "groupId" : "org.scalatest",
      "artifactId" : "scalatest_2.10",
      "version" : "2.0.M5b"
    },
    "scope" : "test"
  },
  {
    "source" : {
      "groupId" : "org.scalanlp",
      "artifactId" : "nak_2.11",
      "version" : "1.3.1"
    },
    "target" : {
      "groupId" : "com.typesafe.scala-logging",
      "artifactId" : "scala-logging_2.11",
      "version" : "3.3.0"
    },
    "scope" : "compile"
  },
  {
    "source" : {
      "groupId" : "org.scalanlp",
      "artifactId" : "nak_2.11",
      "version" : "1.3.1"
    },
    "target" : {
      "groupId" : "org.apache.logging.log4j",
      "artifactId" : "log4j-core",
      "version" : "2.4.1"
    },
    "scope" : "runtime"
  },
  {
    "source" : {
      "groupId" : "org.scalanlp",
      "artifactId" : "nak_2.11",
      "version" : "1.3.1"
    },
    "target" : {
      "groupId" : "org.rogach",
      "artifactId" : "scallop_2.11",
      "version" : "0.9.5"
    },
    "scope" : "compile"
  },
  {
    "source" : {
      "groupId" : "org.scalanlp",
      "artifactId" : "nak_2.11",
      "version" : "1.3.1"
    },
    "target" : {
      "groupId" : "org.scalacheck",
      "artifactId" : "scalacheck_2.11",
      "version" : "1.11.3"
    },
    "scope" : "test"
  },
  {
    "source" : {
      "groupId" : "org.scalanlp",
      "artifactId" : "nak_2.11",
      "version" : "1.3.1"
    },
    "target" : {
      "groupId" : "org.scala-lang",
      "artifactId" : "scala-library",
      "version" : "2.11.8"
    },
    "scope" : "compile"
  },
  {
    "source" : {
      "groupId" : "org.scalanlp",
      "artifactId" : "nak_2.11",
      "version" : "1.3.1"
    },
    "target" : {
      "groupId" : "org.scalanlp",
      "artifactId" : "breeze_2.11",
      "version" : "0.9"
    },
    "scope" : "compile"
  },
  {
    "source" : {
      "groupId" : "org.scalanlp",
      "artifactId" : "nak_2.11",
      "version" : "1.3.1"
    },
    "target" : {
      "groupId" : "org.scalanlp",
      "artifactId" : "breeze-config_2.11",
      "version" : "0.9.1"
    },
    "scope" : "compile"
  },
  {
    "source" : {
      "groupId" : "org.scalanlp",
      "artifactId" : "nak_2.11",
      "version" : "1.3.1"
    },
    "target" : {
      "groupId" : "org.scalanlp",
      "artifactId" : "breeze-natives_2.11",
      "version" : "0.8"
    },
    "scope" : "runtime"
  },
  {
    "source" : {
      "groupId" : "org.scalanlp",
      "artifactId" : "nak_2.11",
      "version" : "1.3.1"
    },
    "target" : {
      "groupId" : "org.scalatest",
      "artifactId" : "scalatest_2.11",
      "version" : "2.1.3"
    },
    "scope" : "test"
  }
]