[
  {
    "groupId" : "org.virtuslab",
    "artifactId" : "pretty-stacktraces_3",
    "version" : "0.0.1",
    "artifactName" : "pretty-stacktraces",
    "projectRef" : {
      "organization" : "virtuslab",
      "repository" : "pretty-stacktraces"
    },
    "description" : "pretty-stacktraces",
    "releaseDate" : 1634045219000,
    "resolver" : null,
    "licenses" : [
      {
        "name" : "Apache License 2.0",
        "shortName" : "Apache-2.0",
        "url" : "https://spdx.org/licenses/Apache-2.0.html"
      }
    ],
    "isNonStandardLib" : false,
    "platform" : "jvm",
    "language" : "3.x"
  }
]